Workbook

Sheet GENERAL SUMMARY
B2: SUMMARY
B11: DATE | D11: PROJECT NAME | E11: PROJECT LOCATION
B12: ='DETAILED ESTIMATE'!B15 -> 46304 | D12: ='DETAILED ESTIMATE'!E15 -> FIFTH THIRD BANK WATSON BLVD | E12: ='DETAILED ESTIMATE'!J15 -> 2711 WATSON BOULEVARD WARNER ROBINS, GA 31093
D13: ='DETAILED ESTIMATE'!E16 -> GROSS AREA: 2000 SF
B15: LINE NO. | C15: CSI DIV. | D15: DESCRIPTION | E15: TOTAL LABOR HOURS | F15: MATERIAL COST | G15: LABOR COST | H15: TOTAL COST
B17: =IF(H17<>"",1+MAX($B$15:B15),"") | C17: ='DETAILED ESTIMATE'!C19 -> 0
B18: =IF(H18<>"",1+MAX($B$15:B17),"") -> 1 | C18: ='DETAILED ESTIMATE'!C20 -> DIV. 01 | D18: =VLOOKUP($C18,'DETAILED ESTIMATE'!$C$20:$R$1258,2,0) -> GENERAL REQUIREMENTS | E18: =VLOOKUP($C18,'DETAILED ESTIMATE'!$C$20:$R$1258,9,0) -> 0 HRS | F18: =(VLOOKUP($C18,'DETAILED ESTIMATE'!$C$20:$R$1258,7,0))+'DETAILED ESTIMATE'!$Q$7*(VLOOKUP($C18,'DETAILED ESTIMATE'!$C$20:$R$1258,7,0))+'DETAILED ESTIMATE'!$Q$9*(VLOOKUP($C18,'DETAILED ESTIMATE'!$C$20:$R$1258,7,0))+'DETAILED ESTIMATE'!$Q$10*((VLOOKUP($C18,'DETAILED ESTIMATE'!$C$20:$R$1258,7,0))+'DETAILED ESTIMATE'!$Q$7*(VLOOKUP($C18,'DETAILED ESTIMATE'!$C$20:$R$1258,7,0))+'DETAILED ESTIMATE'!$Q$9*(VLOOKUP($C18,'DETAILED ESTIMATE'!$C$20:$R$1258,7,0)))+'DETAILED ESTIMATE'!$Q$11*(VLOOKUP($C18,'DETAILED ESTIMATE'!$C$20:$R$1258,7,0)) -> 0 | G18: =(VLOOKUP($C18,'DETAILED ESTIMATE'!$C$20:$R$1258,14,0))+'DETAILED ESTIMATE'!$Q$8*(VLOOKUP($C18,'DETAILED ESTIMATE'!$C$20:$R$1258,14,0))+'DETAILED ESTIMATE'!$Q$9*(VLOOKUP($C18,'DETAILED ESTIMATE'!$C$20:$R$1258,14,0))+'DETAILED ESTIMATE'!$Q$10*((VLOOKUP($C18,'DETAILED ESTIMATE'!$C$20:$R$1258,14,0))+'DETAILED ESTIMATE'!$Q$8*(VLOOKUP($C18,'DETAILED ESTIMATE'!$C$20:$R$1258,14,0))+'DETAILED ESTIMATE'!$Q$9*(VLOOKUP($C18,'DETAILED ESTIMATE'!$C$20:$R$1258,14,0)))+'DETAILED ESTIMATE'!$Q$11*(VLOOKUP($C18,'DETAILED ESTIMATE'!$C$20:$R$1258,14,0)) -> 164818.5 | H18: =VLOOKUP($C18,'DETAILED ESTIMATE'!$C$20:$R$1258,16,0) -> 164818.5
B19: =IF(H19<>"",1+MAX($B$15:B18),"") -> 2 | C19: ='DETAILED ESTIMATE'!C24 -> DIV. 02 | D19: =VLOOKUP($C19,'DETAILED ESTIMATE'!$C$20:$R$1258,2,0) -> EXISTING CONDITIONS | E19: =VLOOKUP($C19,'DETAILED ESTIMATE'!$C$20:$R$1258,9,0) -> 2747 HRS | F19: =(VLOOKUP($C19,'DETAILED ESTIMATE'!$C$20:$R$1258,7,0))+'DETAILED ESTIMATE'!$Q$7*(VLOOKUP($C19,'DETAILED ESTIMATE'!$C$20:$R$1258,7,0))+'DETAILED ESTIMATE'!$Q$9*(VLOOKUP($C19,'DETAILED ESTIMATE'!$C$20:$R$1258,7,0))+'DETAILED ESTIMATE'!$Q$10*((VLOOKUP($C19,'DETAILED ESTIMATE'!$C$20:$R$1258,7,0))+'DETAILED ESTIMATE'!$Q$7*(VLOOKUP($C19,'DETAILED ESTIMATE'!$C$20:$R$1258,7,0))+'DETAILED ESTIMATE'!$Q$9*(VLOOKUP($C19,'DETAILED ESTIMATE'!$C$20:$R$1258,7,0)))+'DETAILED ESTIMATE'!$Q$11*(VLOOKUP($C19,'DETAILED ESTIMATE'!$C$20:$R$1258,7,0)) -> 0 | G19: =(VLOOKUP($C19,'DETAILED ESTIMATE'!$C$20:$R$1258,14,0))+'DETAILED ESTIMATE'!$Q$8*(VLOOKUP($C19,'DETAILED ESTIMATE'!$C$20:$R$1258,14,0))+'DETAILED ESTIMATE'!$Q$9*(VLOOKUP($C19,'DETAILED ESTIMATE'!$C$20:$R$1258,14,0))+'DETAILED ESTIMATE'!$Q$10*((VLOOKUP($C19,'DETAILED ESTIMATE'!$C$20:$R$1258,14,0))+'DETAILED ESTIMATE'!$Q$8*(VLOOKUP($C19,'DETAILED ESTIMATE'!$C$20:$R$1258,14,0))+'DETAILED ESTIMATE'!$Q$9*(VLOOKUP($C19,'DETAILED ESTIMATE'!$C$20:$R$1258,14,0)))+'DETAILED ESTIMATE'!$Q$11*(VLOOKUP($C19,'DETAILED ESTIMATE'!$C$20:$R$1258,14,0)) -> 172757.77 | H19: =VLOOKUP($C19,'DETAILED ESTIMATE'!$C$20:$R$1258,16,0) -> 172757.77
B20: =IF(H20<>"",1+MAX($B$15:B19),"") -> 3 | C20: ='DETAILED ESTIMATE'!C42 -> DIV. 03 | D20: =VLOOKUP($C20,'DETAILED ESTIMATE'!$C$20:$R$1258,2,0) -> CONCRETE | E20: =VLOOKUP($C20,'DETAILED ESTIMATE'!$C$20:$R$1258,9,0) -> 413 HRS | F20: =(VLOOKUP($C20,'DETAILED ESTIMATE'!$C$20:$R$1258,7,0))+'DETAILED ESTIMATE'!$Q$7*(VLOOKUP($C20,'DETAILED ESTIMATE'!$C$20:$R$1258,7,0))+'DETAILED ESTIMATE'!$Q$9*(VLOOKUP($C20,'DETAILED ESTIMATE'!$C$20:$R$1258,7,0))+'DETAILED ESTIMATE'!$Q$10*((VLOOKUP($C20,'DETAILED ESTIMATE'!$C$20:$R$1258,7,0))+'DETAILED ESTIMATE'!$Q$7*(VLOOKUP($C20,'DETAILED ESTIMATE'!$C$20:$R$1258,7,0))+'DETAILED ESTIMATE'!$Q$9*(VLOOKUP($C20,'DETAILED ESTIMATE'!$C$20:$R$1258,7,0)))+'DETAILED ESTIMATE'!$Q$11*(VLOOKUP($C20,'DETAILED ESTIMATE'!$C$20:$R$1258,7,0)) -> 26726.059 | G20: =(VLOOKUP($C20,'DETAILED ESTIMATE'!$C$20:$R$1258,14,0))+'DETAILED ESTIMATE'!$Q$8*(VLOOKUP($C20,'DETAILED ESTIMATE'!$C$20:$R$1258,14,0))+'DETAILED ESTIMATE'!$Q$9*(VLOOKUP($C20,'DETAILED ESTIMATE'!$C$20:$R$1258,14,0))+'DETAILED ESTIMATE'!$Q$10*((VLOOKUP($C20,'DETAILED ESTIMATE'!$C$20:$R$1258,14,0))+'DETAILED ESTIMATE'!$Q$8*(VLOOKUP($C20,'DETAILED ESTIMATE'!$C$20:$R$1258,14,0))+'DETAILED ESTIMATE'!$Q$9*(VLOOKUP($C20,'DETAILED ESTIMATE'!$C$20:$R$1258,14,0)))+'DETAILED ESTIMATE'!$Q$11*(VLOOKUP($C20,'DETAILED ESTIMATE'!$C$20:$R$1258,14,0)) -> 21916.874 | H20: =VLOOKUP($C20,'DETAILED ESTIMATE'!$C$20:$R$1258,16,0) -> 48642.933
B21: =IF(H21<>"",1+MAX($B$15:B20),"") -> 4 | C21: ='DETAILED ESTIMATE'!C75 -> DIV. 04 | D21: =VLOOKUP($C21,'DETAILED ESTIMATE'!$C$20:$R$1258,2,0) -> MASONRY | E21: =VLOOKUP($C21,'DETAILED ESTIMATE'!$C$20:$R$1258,9,0) -> 224 HRS | F21: =(VLOOKUP($C21,'DETAILED ESTIMATE'!$C$20:$R$1258,7,0))+'DETAILED ESTIMATE'!$Q$7*(VLOOKUP($C21,'DETAILED ESTIMATE'!$C$20:$R$1258,7,0))+'DETAILED ESTIMATE'!$Q$9*(VLOOKUP($C21,'DETAILED ESTIMATE'!$C$20:$R$1258,7,0))+'DETAILED ESTIMATE'!$Q$10*((VLOOKUP($C21,'DETAILED ESTIMATE'!$C$20:$R$1258,7,0))+'DETAILED ESTIMATE'!$Q$7*(VLOOKUP($C21,'DETAILED ESTIMATE'!$C$20:$R$1258,7,0))+'DETAILED ESTIMATE'!$Q$9*(VLOOKUP($C21,'DETAILED ESTIMATE'!$C$20:$R$1258,7,0)))+'DETAILED ESTIMATE'!$Q$11*(VLOOKUP($C21,'DETAILED ESTIMATE'!$C$20:$R$1258,7,0)) -> 6160.8637 | G21: =(VLOOKUP($C21,'DETAILED ESTIMATE'!$C$20:$R$1258,14,0))+'DETAILED ESTIMATE'!$Q$8*(VLOOKUP($C21,'DETAILED ESTIMATE'!$C$20:$R$1258,14,0))+'DETAILED ESTIMATE'!$Q$9*(VLOOKUP($C21,'DETAILED ESTIMATE'!$C$20:$R$1258,14,0))+'DETAILED ESTIMATE'!$Q$10*((VLOOKUP($C21,'DETAILED ESTIMATE'!$C$20:$R$1258,14,0))+'DETAILED ESTIMATE'!$Q$8*(VLOOKUP($C21,'DETAILED ESTIMATE'!$C$20:$R$1258,14,0))+'DETAILED ESTIMATE'!$Q$9*(VLOOKUP($C21,'DETAILED ESTIMATE'!$C$20:$R$1258,14,0)))+'DETAILED ESTIMATE'!$Q$11*(VLOOKUP($C21,'DETAILED ESTIMATE'!$C$20:$R$1258,14,0)) -> 11128.622 | H21: =VLOOKUP($C21,'DETAILED ESTIMATE'!$C$20:$R$1258,16,0) -> 17289.486
B22: =IF(H22<>"",1+MAX($B$15:B21),"") -> 5 | C22: ='DETAILED ESTIMATE'!C90 -> DIV. 05 | D22: =VLOOKUP($C22,'DETAILED ESTIMATE'!$C$20:$R$1258,2,0) -> METALS | E22: =VLOOKUP($C22,'DETAILED ESTIMATE'!$C$20:$R$1258,9,0) -> 777 HRS | F22: =(VLOOKUP($C22,'DETAILED ESTIMATE'!$C$20:$R$1258,7,0))+'DETAILED ESTIMATE'!$Q$7*(VLOOKUP($C22,'DETAILED ESTIMATE'!$C$20:$R$1258,7,0))+'DETAILED ESTIMATE'!$Q$9*(VLOOKUP($C22,'DETAILED ESTIMATE'!$C$20:$R$1258,7,0))+'DETAILED ESTIMATE'!$Q$10*((VLOOKUP($C22,'DETAILED ESTIMATE'!$C$20:$R$1258,7,0))+'DETAILED ESTIMATE'!$Q$7*(VLOOKUP($C22,'DETAILED ESTIMATE'!$C$20:$R$1258,7,0))+'DETAILED ESTIMATE'!$Q$9*(VLOOKUP($C22,'DETAILED ESTIMATE'!$C$20:$R$1258,7,0)))+'DETAILED ESTIMATE'!$Q$11*(VLOOKUP($C22,'DETAILED ESTIMATE'!$C$20:$R$1258,7,0)) -> 90177.103 | G22: =(VLOOKUP($C22,'DETAILED ESTIMATE'!$C$20:$R$1258,14,0))+'DETAILED ESTIMATE'!$Q$8*(VLOOKUP($C22,'DETAILED ESTIMATE'!$C$20:$R$1258,14,0))+'DETAILED ESTIMATE'!$Q$9*(VLOOKUP($C22,'DETAILED ESTIMATE'!$C$20:$R$1258,14,0))+'DETAILED ESTIMATE'!$Q$10*((VLOOKUP($C22,'DETAILED ESTIMATE'!$C$20:$R$1258,14,0))+'DETAILED ESTIMATE'!$Q$8*(VLOOKUP($C22,'DETAILED ESTIMATE'!$C$20:$R$1258,14,0))+'DETAILED ESTIMATE'!$Q$9*(VLOOKUP($C22,'DETAILED ESTIMATE'!$C$20:$R$1258,14,0)))+'DETAILED ESTIMATE'!$Q$11*(VLOOKUP($C22,'DETAILED ESTIMATE'!$C$20:$R$1258,14,0)) -> 58048.816 | H22: =VLOOKUP($C22,'DETAILED ESTIMATE'!$C$20:$R$1258,16,0) -> 148225.92
B23: =IF(H23<>"",1+MAX($B$15:B22),"") -> 6 | C23: ='DETAILED ESTIMATE'!C155 -> DIV. 06 | D23: =VLOOKUP($C23,'DETAILED ESTIMATE'!$C$20:$R$1258,2,0) -> WOOD, PLASTICS AND COMPOSITES | E23: =VLOOKUP($C23,'DETAILED ESTIMATE'!$C$20:$R$1258,9,0) -> 284 HRS | F23: =(VLOOKUP($C23,'DETAILED ESTIMATE'!$C$20:$R$1258,7,0))+'DETAILED ESTIMATE'!$Q$7*(VLOOKUP($C23,'DETAILED ESTIMATE'!$C$20:$R$1258,7,0))+'DETAILED ESTIMATE'!$Q$9*(VLOOKUP($C23,'DETAILED ESTIMATE'!$C$20:$R$1258,7,0))+'DETAILED ESTIMATE'!$Q$10*((VLOOKUP($C23,'DETAILED ESTIMATE'!$C$20:$R$1258,7,0))+'DETAILED ESTIMATE'!$Q$7*(VLOOKUP($C23,'DETAILED ESTIMATE'!$C$20:$R$1258,7,0))+'DETAILED ESTIMATE'!$Q$9*(VLOOKUP($C23,'DETAILED ESTIMATE'!$C$20:$R$1258,7,0)))+'DETAILED ESTIMATE'!$Q$11*(VLOOKUP($C23,'DETAILED ESTIMATE'!$C$20:$R$1258,7,0)) -> 66000.408 | G23: =(VLOOKUP($C23,'DETAILED ESTIMATE'!$C$20:$R$1258,14,0))+'DETAILED ESTIMATE'!$Q$8*(VLOOKUP($C23,'DETAILED ESTIMATE'!$C$20:$R$1258,14,0))+'DETAILED ESTIMATE'!$Q$9*(VLOOKUP($C23,'DETAILED ESTIMATE'!$C$20:$R$1258,14,0))+'DETAILED ESTIMATE'!$Q$10*((VLOOKUP($C23,'DETAILED ESTIMATE'!$C$20:$R$1258,14,0))+'DETAILED ESTIMATE'!$Q$8*(VLOOKUP($C23,'DETAILED ESTIMATE'!$C$20:$R$1258,14,0))+'DETAILED ESTIMATE'!$Q$9*(VLOOKUP($C23,'DETAILED ESTIMATE'!$C$20:$R$1258,14,0)))+'DETAILED ESTIMATE'!$Q$11*(VLOOKUP($C23,'DETAILED ESTIMATE'!$C$20:$R$1258,14,0)) -> 15734.352 | H23: =VLOOKUP($C23,'DETAILED ESTIMATE'!$C$20:$R$1258,16,0) -> 81734.759
B24: =IF(H24<>"",1+MAX($B$15:B23),"") -> 7 | C24: ='DETAILED ESTIMATE'!C266 -> DIV. 07 | D24: =VLOOKUP($C24,'DETAILED ESTIMATE'!$C$20:$R$1258,2,0) -> THERMAL AND MOISTURE PROTECTION | E24: =VLOOKUP($C24,'DETAILED ESTIMATE'!$C$20:$R$1258,9,0) -> 855 HRS | F24: =(VLOOKUP($C24,'DETAILED ESTIMATE'!$C$20:$R$1258,7,0))+'DETAILED ESTIMATE'!$Q$7*(VLOOKUP($C24,'DETAILED ESTIMATE'!$C$20:$R$1258,7,0))+'DETAILED ESTIMATE'!$Q$9*(VLOOKUP($C24,'DETAILED ESTIMATE'!$C$20:$R$1258,7,0))+'DETAILED ESTIMATE'!$Q$10*((VLOOKUP($C24,'DETAILED ESTIMATE'!$C$20:$R$1258,7,0))+'DETAILED ESTIMATE'!$Q$7*(VLOOKUP($C24,'DETAILED ESTIMATE'!$C$20:$R$1258,7,0))+'DETAILED ESTIMATE'!$Q$9*(VLOOKUP($C24,'DETAILED ESTIMATE'!$C$20:$R$1258,7,0)))+'DETAILED ESTIMATE'!$Q$11*(VLOOKUP($C24,'DETAILED ESTIMATE'!$C$20:$R$1258,7,0)) -> 72497.177 | G24: =(VLOOKUP($C24,'DETAILED ESTIMATE'!$C$20:$R$1258,14,0))+'DETAILED ESTIMATE'!$Q$8*(VLOOKUP($C24,'DETAILED ESTIMATE'!$C$20:$R$1258,14,0))+'DETAILED ESTIMATE'!$Q$9*(VLOOKUP($C24,'DETAILED ESTIMATE'!$C$20:$R$1258,14,0))+'DETAILED ESTIMATE'!$Q$10*((VLOOKUP($C24,'DETAILED ESTIMATE'!$C$20:$R$1258,14,0))+'DETAILED ESTIMATE'!$Q$8*(VLOOKUP($C24,'DETAILED ESTIMATE'!$C$20:$R$1258,14,0))+'DETAILED ESTIMATE'!$Q$9*(VLOOKUP($C24,'DETAILED ESTIMATE'!$C$20:$R$1258,14,0)))+'DETAILED ESTIMATE'!$Q$11*(VLOOKUP($C24,'DETAILED ESTIMATE'!$C$20:$R$1258,14,0)) -> 44027.775 | H24: =VLOOKUP($C24,'DETAILED ESTIMATE'!$C$20:$R$1258,16,0) -> 116524.95
B25: =IF(H25<>"",1+MAX($B$15:B24),"") -> 8 | C25: ='DETAILED ESTIMATE'!C344 -> DIV. 08 | D25: =VLOOKUP($C25,'DETAILED ESTIMATE'!$C$20:$R$1258,2,0) -> OPENINGS | E25: =VLOOKUP($C25,'DETAILED ESTIMATE'!$C$20:$R$1258,9,0) -> 213 HRS | F25: =(VLOOKUP($C25,'DETAILED ESTIMATE'!$C$20:$R$1258,7,0))+'DETAILED ESTIMATE'!$Q$7*(VLOOKUP($C25,'DETAILED ESTIMATE'!$C$20:$R$1258,7,0))+'DETAILED ESTIMATE'!$Q$9*(VLOOKUP($C25,'DETAILED ESTIMATE'!$C$20:$R$1258,7,0))+'DETAILED ESTIMATE'!$Q$10*((VLOOKUP($C25,'DETAILED ESTIMATE'!$C$20:$R$1258,7,0))+'DETAILED ESTIMATE'!$Q$7*(VLOOKUP($C25,'DETAILED ESTIMATE'!$C$20:$R$1258,7,0))+'DETAILED ESTIMATE'!$Q$9*(VLOOKUP($C25,'DETAILED ESTIMATE'!$C$20:$R$1258,7,0)))+'DETAILED ESTIMATE'!$Q$11*(VLOOKUP($C25,'DETAILED ESTIMATE'!$C$20:$R$1258,7,0)) -> 100158.24 | G25: =(VLOOKUP($C25,'DETAILED ESTIMATE'!$C$20:$R$1258,14,0))+'DETAILED ESTIMATE'!$Q$8*(VLOOKUP($C25,'DETAILED ESTIMATE'!$C$20:$R$1258,14,0))+'DETAILED ESTIMATE'!$Q$9*(VLOOKUP($C25,'DETAILED ESTIMATE'!$C$20:$R$1258,14,0))+'DETAILED ESTIMATE'!$Q$10*((VLOOKUP($C25,'DETAILED ESTIMATE'!$C$20:$R$1258,14,0))+'DETAILED ESTIMATE'!$Q$8*(VLOOKUP($C25,'DETAILED ESTIMATE'!$C$20:$R$1258,14,0))+'DETAILED ESTIMATE'!$Q$9*(VLOOKUP($C25,'DETAILED ESTIMATE'!$C$20:$R$1258,14,0)))+'DETAILED ESTIMATE'!$Q$11*(VLOOKUP($C25,'DETAILED ESTIMATE'!$C$20:$R$1258,14,0)) -> 11901.292 | H25: =VLOOKUP($C25,'DETAILED ESTIMATE'!$C$20:$R$1258,16,0) -> 112059.54
B26: =IF(H26<>"",1+MAX($B$15:B25),"") -> 9 | C26: ='DETAILED ESTIMATE'!C392 -> DIV. 09 | D26: =VLOOKUP($C26,'DETAILED ESTIMATE'!$C$20:$R$1258,2,0) -> FINISHES | E26: =VLOOKUP($C26,'DETAILED ESTIMATE'!$C$20:$R$1258,9,0) -> 1025 HRS | F26: =(VLOOKUP($C26,'DETAILED ESTIMATE'!$C$20:$R$1258,7,0))+'DETAILED ESTIMATE'!$Q$7*(VLOOKUP($C26,'DETAILED ESTIMATE'!$C$20:$R$1258,7,0))+'DETAILED ESTIMATE'!$Q$9*(VLOOKUP($C26,'DETAILED ESTIMATE'!$C$20:$R$1258,7,0))+'DETAILED ESTIMATE'!$Q$10*((VLOOKUP($C26,'DETAILED ESTIMATE'!$C$20:$R$1258,7,0))+'DETAILED ESTIMATE'!$Q$7*(VLOOKUP($C26,'DETAILED ESTIMATE'!$C$20:$R$1258,7,0))+'DETAILED ESTIMATE'!$Q$9*(VLOOKUP($C26,'DETAILED ESTIMATE'!$C$20:$R$1258,7,0)))+'DETAILED ESTIMATE'!$Q$11*(VLOOKUP($C26,'DETAILED ESTIMATE'!$C$20:$R$1258,7,0)) -> 85410.622 | G26: =(VLOOKUP($C26,'DETAILED ESTIMATE'!$C$20:$R$1258,14,0))+'DETAILED ESTIMATE'!$Q$8*(VLOOKUP($C26,'DETAILED ESTIMATE'!$C$20:$R$1258,14,0))+'DETAILED ESTIMATE'!$Q$9*(VLOOKUP($C26,'DETAILED ESTIMATE'!$C$20:$R$1258,14,0))+'DETAILED ESTIMATE'!$Q$10*((VLOOKUP($C26,'DETAILED ESTIMATE'!$C$20:$R$1258,14,0))+'DETAILED ESTIMATE'!$Q$8*(VLOOKUP($C26,'DETAILED ESTIMATE'!$C$20:$R$1258,14,0))+'DETAILED ESTIMATE'!$Q$9*(VLOOKUP($C26,'DETAILED ESTIMATE'!$C$20:$R$1258,14,0)))+'DETAILED ESTIMATE'!$Q$11*(VLOOKUP($C26,'DETAILED ESTIMATE'!$C$20:$R$1258,14,0)) -> 54520.862 | H26: =VLOOKUP($C26,'DETAILED ESTIMATE'!$C$20:$R$1258,16,0) -> 139931.48
B27: =IF(H27<>"",1+MAX($B$15:B26),"") -> 10 | C27: ='DETAILED ESTIMATE'!C547 -> DIV. 10 | D27: =VLOOKUP($C27,'DETAILED ESTIMATE'!$C$20:$R$1258,2,0) -> SPECIALTIES | E27: =VLOOKUP($C27,'DETAILED ESTIMATE'!$C$20:$R$1258,9,0) -> 15 HRS | F27: =(VLOOKUP($C27,'DETAILED ESTIMATE'!$C$20:$R$1258,7,0))+'DETAILED ESTIMATE'!$Q$7*(VLOOKUP($C27,'DETAILED ESTIMATE'!$C$20:$R$1258,7,0))+'DETAILED ESTIMATE'!$Q$9*(VLOOKUP($C27,'DETAILED ESTIMATE'!$C$20:$R$1258,7,0))+'DETAILED ESTIMATE'!$Q$10*((VLOOKUP($C27,'DETAILED ESTIMATE'!$C$20:$R$1258,7,0))+'DETAILED ESTIMATE'!$Q$7*(VLOOKUP($C27,'DETAILED ESTIMATE'!$C$20:$R$1258,7,0))+'DETAILED ESTIMATE'!$Q$9*(VLOOKUP($C27,'DETAILED ESTIMATE'!$C$20:$R$1258,7,0)))+'DETAILED ESTIMATE'!$Q$11*(VLOOKUP($C27,'DETAILED ESTIMATE'!$C$20:$R$1258,7,0)) -> 3690.2857 | G27: =(VLOOKUP($C27,'DETAILED ESTIMATE'!$C$20:$R$1258,14,0))+'DETAILED ESTIMATE'!$Q$8*(VLOOKUP($C27,'DETAILED ESTIMATE'!$C$20:$R$1258,14,0))+'DETAILED ESTIMATE'!$Q$9*(VLOOKUP($C27,'DETAILED ESTIMATE'!$C$20:$R$1258,14,0))+'DETAILED ESTIMATE'!$Q$10*((VLOOKUP($C27,'DETAILED ESTIMATE'!$C$20:$R$1258,14,0))+'DETAILED ESTIMATE'!$Q$8*(VLOOKUP($C27,'DETAILED ESTIMATE'!$C$20:$R$1258,14,0))+'DETAILED ESTIMATE'!$Q$9*(VLOOKUP($C27,'DETAILED ESTIMATE'!$C$20:$R$1258,14,0)))+'DETAILED ESTIMATE'!$Q$11*(VLOOKUP($C27,'DETAILED ESTIMATE'!$C$20:$R$1258,14,0)) -> 833.69235 | H27: =VLOOKUP($C27,'DETAILED ESTIMATE'!$C$20:$R$1258,16,0) -> 4523.9781
B28: =IF(H28<>"",1+MAX($B$15:B27),"") -> 11 | C28: ='DETAILED ESTIMATE'!C575 -> DIV. 11 | D28: =VLOOKUP($C28,'DETAILED ESTIMATE'!$C$20:$R$1258,2,0) -> EQUIPMENT | E28: =VLOOKUP($C28,'DETAILED ESTIMATE'!$C$20:$R$1258,9,0) -> 27 HRS | F28: =(VLOOKUP($C28,'DETAILED ESTIMATE'!$C$20:$R$1258,7,0))+'DETAILED ESTIMATE'!$Q$7*(VLOOKUP($C28,'DETAILED ESTIMATE'!$C$20:$R$1258,7,0))+'DETAILED ESTIMATE'!$Q$9*(VLOOKUP($C28,'DETAILED ESTIMATE'!$C$20:$R$1258,7,0))+'DETAILED ESTIMATE'!$Q$10*((VLOOKUP($C28,'DETAILED ESTIMATE'!$C$20:$R$1258,7,0))+'DETAILED ESTIMATE'!$Q$7*(VLOOKUP($C28,'DETAILED ESTIMATE'!$C$20:$R$1258,7,0))+'DETAILED ESTIMATE'!$Q$9*(VLOOKUP($C28,'DETAILED ESTIMATE'!$C$20:$R$1258,7,0)))+'DETAILED ESTIMATE'!$Q$11*(VLOOKUP($C28,'DETAILED ESTIMATE'!$C$20:$R$1258,7,0)) -> 28358.181 | G28: =(VLOOKUP($C28,'DETAILED ESTIMATE'!$C$20:$R$1258,14,0))+'DETAILED ESTIMATE'!$Q$8*(VLOOKUP($C28,'DETAILED ESTIMATE'!$C$20:$R$1258,14,0))+'DETAILED ESTIMATE'!$Q$9*(VLOOKUP($C28,'DETAILED ESTIMATE'!$C$20:$R$1258,14,0))+'DETAILED ESTIMATE'!$Q$10*((VLOOKUP($C28,'DETAILED ESTIMATE'!$C$20:$R$1258,14,0))+'DETAILED ESTIMATE'!$Q$8*(VLOOKUP($C28,'DETAILED ESTIMATE'!$C$20:$R$1258,14,0))+'DETAILED ESTIMATE'!$Q$9*(VLOOKUP($C28,'DETAILED ESTIMATE'!$C$20:$R$1258,14,0)))+'DETAILED ESTIMATE'!$Q$11*(VLOOKUP($C28,'DETAILED ESTIMATE'!$C$20:$R$1258,14,0)) -> 1625.946 | H28: =VLOOKUP($C28,'DETAILED ESTIMATE'!$C$20:$R$1258,16,0) -> 29984.127
B29: =IF(H29<>"",1+MAX($B$15:B28),"") -> 12 | C29: ='DETAILED ESTIMATE'!C589 -> DIV. 12 | D29: =VLOOKUP($C29,'DETAILED ESTIMATE'!$C$20:$R$1258,2,0) -> FURNISHINGS | E29: =VLOOKUP($C29,'DETAILED ESTIMATE'!$C$20:$R$1258,9,0) -> 205 HRS | F29: =(VLOOKUP($C29,'DETAILED ESTIMATE'!$C$20:$R$1258,7,0))+'DETAILED ESTIMATE'!$Q$7*(VLOOKUP($C29,'DETAILED ESTIMATE'!$C$20:$R$1258,7,0))+'DETAILED ESTIMATE'!$Q$9*(VLOOKUP($C29,'DETAILED ESTIMATE'!$C$20:$R$1258,7,0))+'DETAILED ESTIMATE'!$Q$10*((VLOOKUP($C29,'DETAILED ESTIMATE'!$C$20:$R$1258,7,0))+'DETAILED ESTIMATE'!$Q$7*(VLOOKUP($C29,'DETAILED ESTIMATE'!$C$20:$R$1258,7,0))+'DETAILED ESTIMATE'!$Q$9*(VLOOKUP($C29,'DETAILED ESTIMATE'!$C$20:$R$1258,7,0)))+'DETAILED ESTIMATE'!$Q$11*(VLOOKUP($C29,'DETAILED ESTIMATE'!$C$20:$R$1258,7,0)) -> 39362.729 | G29: =(VLOOKUP($C29,'DETAILED ESTIMATE'!$C$20:$R$1258,14,0))+'DETAILED ESTIMATE'!$Q$8*(VLOOKUP($C29,'DETAILED ESTIMATE'!$C$20:$R$1258,14,0))+'DETAILED ESTIMATE'!$Q$9*(VLOOKUP($C29,'DETAILED ESTIMATE'!$C$20:$R$1258,14,0))+'DETAILED ESTIMATE'!$Q$10*((VLOOKUP($C29,'DETAILED ESTIMATE'!$C$20:$R$1258,14,0))+'DETAILED ESTIMATE'!$Q$8*(VLOOKUP($C29,'DETAILED ESTIMATE'!$C$20:$R$1258,14,0))+'DETAILED ESTIMATE'!$Q$9*(VLOOKUP($C29,'DETAILED ESTIMATE'!$C$20:$R$1258,14,0)))+'DETAILED ESTIMATE'!$Q$11*(VLOOKUP($C29,'DETAILED ESTIMATE'!$C$20:$R$1258,14,0)) -> 10903.676 | H29: =VLOOKUP($C29,'DETAILED ESTIMATE'!$C$20:$R$1258,16,0) -> 50266.405
B30: =IF(H30<>"",1+MAX($B$15:B29),"") -> 13 | C30: ='DETAILED ESTIMATE'!C660 -> DIV. 22 | D30: =VLOOKUP($C30,'DETAILED ESTIMATE'!$C$20:$R$1258,2,0) -> PLUMBING | E30: =VLOOKUP($C30,'DETAILED ESTIMATE'!$C$20:$R$1258,9,0) -> 381 HRS | F30: =(VLOOKUP($C30,'DETAILED ESTIMATE'!$C$20:$R$1258,7,0))+'DETAILED ESTIMATE'!$Q$7*(VLOOKUP($C30,'DETAILED ESTIMATE'!$C$20:$R$1258,7,0))+'DETAILED ESTIMATE'!$Q$9*(VLOOKUP($C30,'DETAILED ESTIMATE'!$C$20:$R$1258,7,0))+'DETAILED ESTIMATE'!$Q$10*((VLOOKUP($C30,'DETAILED ESTIMATE'!$C$20:$R$1258,7,0))+'DETAILED ESTIMATE'!$Q$7*(VLOOKUP($C30,'DETAILED ESTIMATE'!$C$20:$R$1258,7,0))+'DETAILED ESTIMATE'!$Q$9*(VLOOKUP($C30,'DETAILED ESTIMATE'!$C$20:$R$1258,7,0)))+'DETAILED ESTIMATE'!$Q$11*(VLOOKUP($C30,'DETAILED ESTIMATE'!$C$20:$R$1258,7,0)) -> 49734.179 | G30: =(VLOOKUP($C30,'DETAILED ESTIMATE'!$C$20:$R$1258,14,0))+'DETAILED ESTIMATE'!$Q$8*(VLOOKUP($C30,'DETAILED ESTIMATE'!$C$20:$R$1258,14,0))+'DETAILED ESTIMATE'!$Q$9*(VLOOKUP($C30,'DETAILED ESTIMATE'!$C$20:$R$1258,14,0))+'DETAILED ESTIMATE'!$Q$10*((VLOOKUP($C30,'DETAILED ESTIMATE'!$C$20:$R$1258,14,0))+'DETAILED ESTIMATE'!$Q$8*(VLOOKUP($C30,'DETAILED ESTIMATE'!$C$20:$R$1258,14,0))+'DETAILED ESTIMATE'!$Q$9*(VLOOKUP($C30,'DETAILED ESTIMATE'!$C$20:$R$1258,14,0)))+'DETAILED ESTIMATE'!$Q$11*(VLOOKUP($C30,'DETAILED ESTIMATE'!$C$20:$R$1258,14,0)) -> 23664.705 | H30: =VLOOKUP($C30,'DETAILED ESTIMATE'!$C$20:$R$1258,16,0) -> 73398.884
B31: =IF(H31<>"",1+MAX($B$15:B30),"") -> 14 | C31: ='DETAILED ESTIMATE'!C739 -> DIV. 23 | D31: =VLOOKUP($C31,'DETAILED ESTIMATE'!$C$20:$R$1258,2,0) -> HEATING, VENTILATION AND AIR CONDITIONING (HVAC) | E31: =VLOOKUP($C31,'DETAILED ESTIMATE'!$C$20:$R$1258,9,0) -> 320 HRS | F31: =(VLOOKUP($C31,'DETAILED ESTIMATE'!$C$20:$R$1258,7,0))+'DETAILED ESTIMATE'!$Q$7*(VLOOKUP($C31,'DETAILED ESTIMATE'!$C$20:$R$1258,7,0))+'DETAILED ESTIMATE'!$Q$9*(VLOOKUP($C31,'DETAILED ESTIMATE'!$C$20:$R$1258,7,0))+'DETAILED ESTIMATE'!$Q$10*((VLOOKUP($C31,'DETAILED ESTIMATE'!$C$20:$R$1258,7,0))+'DETAILED ESTIMATE'!$Q$7*(VLOOKUP($C31,'DETAILED ESTIMATE'!$C$20:$R$1258,7,0))+'DETAILED ESTIMATE'!$Q$9*(VLOOKUP($C31,'DETAILED ESTIMATE'!$C$20:$R$1258,7,0)))+'DETAILED ESTIMATE'!$Q$11*(VLOOKUP($C31,'DETAILED ESTIMATE'!$C$20:$R$1258,7,0)) -> 58771.329 | G31: =(VLOOKUP($C31,'DETAILED ESTIMATE'!$C$20:$R$1258,14,0))+'DETAILED ESTIMATE'!$Q$8*(VLOOKUP($C31,'DETAILED ESTIMATE'!$C$20:$R$1258,14,0))+'DETAILED ESTIMATE'!$Q$9*(VLOOKUP($C31,'DETAILED ESTIMATE'!$C$20:$R$1258,14,0))+'DETAILED ESTIMATE'!$Q$10*((VLOOKUP($C31,'DETAILED ESTIMATE'!$C$20:$R$1258,14,0))+'DETAILED ESTIMATE'!$Q$8*(VLOOKUP($C31,'DETAILED ESTIMATE'!$C$20:$R$1258,14,0))+'DETAILED ESTIMATE'!$Q$9*(VLOOKUP($C31,'DETAILED ESTIMATE'!$C$20:$R$1258,14,0)))+'DETAILED ESTIMATE'!$Q$11*(VLOOKUP($C31,'DETAILED ESTIMATE'!$C$20:$R$1258,14,0)) -> 19414.527 | H31: =VLOOKUP($C31,'DETAILED ESTIMATE'!$C$20:$R$1258,16,0) -> 78185.855
B32: =IF(H32<>"",1+MAX($B$15:B31),"") -> 15 | C32: ='DETAILED ESTIMATE'!C822 -> DIV. 26 | D32: =VLOOKUP($C32,'DETAILED ESTIMATE'!$C$20:$R$1258,2,0) -> ELECTRICAL | E32: =VLOOKUP($C32,'DETAILED ESTIMATE'!$C$20:$R$1258,9,0) -> 759 HRS | F32: =(VLOOKUP($C32,'DETAILED ESTIMATE'!$C$20:$R$1258,7,0))+'DETAILED ESTIMATE'!$Q$7*(VLOOKUP($C32,'DETAILED ESTIMATE'!$C$20:$R$1258,7,0))+'DETAILED ESTIMATE'!$Q$9*(VLOOKUP($C32,'DETAILED ESTIMATE'!$C$20:$R$1258,7,0))+'DETAILED ESTIMATE'!$Q$10*((VLOOKUP($C32,'DETAILED ESTIMATE'!$C$20:$R$1258,7,0))+'DETAILED ESTIMATE'!$Q$7*(VLOOKUP($C32,'DETAILED ESTIMATE'!$C$20:$R$1258,7,0))+'DETAILED ESTIMATE'!$Q$9*(VLOOKUP($C32,'DETAILED ESTIMATE'!$C$20:$R$1258,7,0)))+'DETAILED ESTIMATE'!$Q$11*(VLOOKUP($C32,'DETAILED ESTIMATE'!$C$20:$R$1258,7,0)) -> 236144.19 | G32: =(VLOOKUP($C32,'DETAILED ESTIMATE'!$C$20:$R$1258,14,0))+'DETAILED ESTIMATE'!$Q$8*(VLOOKUP($C32,'DETAILED ESTIMATE'!$C$20:$R$1258,14,0))+'DETAILED ESTIMATE'!$Q$9*(VLOOKUP($C32,'DETAILED ESTIMATE'!$C$20:$R$1258,14,0))+'DETAILED ESTIMATE'!$Q$10*((VLOOKUP($C32,'DETAILED ESTIMATE'!$C$20:$R$1258,14,0))+'DETAILED ESTIMATE'!$Q$8*(VLOOKUP($C32,'DETAILED ESTIMATE'!$C$20:$R$1258,14,0))+'DETAILED ESTIMATE'!$Q$9*(VLOOKUP($C32,'DETAILED ESTIMATE'!$C$20:$R$1258,14,0)))+'DETAILED ESTIMATE'!$Q$11*(VLOOKUP($C32,'DETAILED ESTIMATE'!$C$20:$R$1258,14,0)) -> 49138.347 | H32: =VLOOKUP($C32,'DETAILED ESTIMATE'!$C$20:$R$1258,16,0) -> 285282.53
B33: =IF(H33<>"",1+MAX($B$15:B32),"") -> 16 | C33: ='DETAILED ESTIMATE'!C970 -> DIV. 28 | D33: =VLOOKUP($C33,'DETAILED ESTIMATE'!$C$20:$R$1258,2,0) -> ELECTRONIC SAFETY AND SECURITY | E33: =VLOOKUP($C33,'DETAILED ESTIMATE'!$C$20:$R$1258,9,0) -> 140 HRS | F33: =(VLOOKUP($C33,'DETAILED ESTIMATE'!$C$20:$R$1258,7,0))+'DETAILED ESTIMATE'!$Q$7*(VLOOKUP($C33,'DETAILED ESTIMATE'!$C$20:$R$1258,7,0))+'DETAILED ESTIMATE'!$Q$9*(VLOOKUP($C33,'DETAILED ESTIMATE'!$C$20:$R$1258,7,0))+'DETAILED ESTIMATE'!$Q$10*((VLOOKUP($C33,'DETAILED ESTIMATE'!$C$20:$R$1258,7,0))+'DETAILED ESTIMATE'!$Q$7*(VLOOKUP($C33,'DETAILED ESTIMATE'!$C$20:$R$1258,7,0))+'DETAILED ESTIMATE'!$Q$9*(VLOOKUP($C33,'DETAILED ESTIMATE'!$C$20:$R$1258,7,0)))+'DETAILED ESTIMATE'!$Q$11*(VLOOKUP($C33,'DETAILED ESTIMATE'!$C$20:$R$1258,7,0)) -> 30241.835 | G33: =(VLOOKUP($C33,'DETAILED ESTIMATE'!$C$20:$R$1258,14,0))+'DETAILED ESTIMATE'!$Q$8*(VLOOKUP($C33,'DETAILED ESTIMATE'!$C$20:$R$1258,14,0))+'DETAILED ESTIMATE'!$Q$9*(VLOOKUP($C33,'DETAILED ESTIMATE'!$C$20:$R$1258,14,0))+'DETAILED ESTIMATE'!$Q$10*((VLOOKUP($C33,'DETAILED ESTIMATE'!$C$20:$R$1258,14,0))+'DETAILED ESTIMATE'!$Q$8*(VLOOKUP($C33,'DETAILED ESTIMATE'!$C$20:$R$1258,14,0))+'DETAILED ESTIMATE'!$Q$9*(VLOOKUP($C33,'DETAILED ESTIMATE'!$C$20:$R$1258,14,0)))+'DETAILED ESTIMATE'!$Q$11*(VLOOKUP($C33,'DETAILED ESTIMATE'!$C$20:$R$1258,14,0)) -> 8932.1232 | H33: =VLOOKUP($C33,'DETAILED ESTIMATE'!$C$20:$R$1258,16,0) -> 39173.959
B34: =IF(H34<>"",1+MAX($B$15:B33),"") -> 17 | C34: ='DETAILED ESTIMATE'!C1022 -> DIV. 31 | D34: =VLOOKUP($C34,'DETAILED ESTIMATE'!$C$20:$R$1258,2,0) -> EARTHWORK | E34: =VLOOKUP($C34,'DETAILED ESTIMATE'!$C$20:$R$1258,9,0) -> 294 HRS | F34: =(VLOOKUP($C34,'DETAILED ESTIMATE'!$C$20:$R$1258,7,0))+'DETAILED ESTIMATE'!$Q$7*(VLOOKUP($C34,'DETAILED ESTIMATE'!$C$20:$R$1258,7,0))+'DETAILED ESTIMATE'!$Q$9*(VLOOKUP($C34,'DETAILED ESTIMATE'!$C$20:$R$1258,7,0))+'DETAILED ESTIMATE'!$Q$10*((VLOOKUP($C34,'DETAILED ESTIMATE'!$C$20:$R$1258,7,0))+'DETAILED ESTIMATE'!$Q$7*(VLOOKUP($C34,'DETAILED ESTIMATE'!$C$20:$R$1258,7,0))+'DETAILED ESTIMATE'!$Q$9*(VLOOKUP($C34,'DETAILED ESTIMATE'!$C$20:$R$1258,7,0)))+'DETAILED ESTIMATE'!$Q$11*(VLOOKUP($C34,'DETAILED ESTIMATE'!$C$20:$R$1258,7,0)) -> 0 | G34: =(VLOOKUP($C34,'DETAILED ESTIMATE'!$C$20:$R$1258,14,0))+'DETAILED ESTIMATE'!$Q$8*(VLOOKUP($C34,'DETAILED ESTIMATE'!$C$20:$R$1258,14,0))+'DETAILED ESTIMATE'!$Q$9*(VLOOKUP($C34,'DETAILED ESTIMATE'!$C$20:$R$1258,14,0))+'DETAILED ESTIMATE'!$Q$10*((VLOOKUP($C34,'DETAILED ESTIMATE'!$C$20:$R$1258,14,0))+'DETAILED ESTIMATE'!$Q$8*(VLOOKUP($C34,'DETAILED ESTIMATE'!$C$20:$R$1258,14,0))+'DETAILED ESTIMATE'!$Q$9*(VLOOKUP($C34,'DETAILED ESTIMATE'!$C$20:$R$1258,14,0)))+'DETAILED ESTIMATE'!$Q$11*(VLOOKUP($C34,'DETAILED ESTIMATE'!$C$20:$R$1258,14,0)) -> 12926.431 | H34: =VLOOKUP($C34,'DETAILED ESTIMATE'!$C$20:$R$1258,16,0) -> 12926.431
B35: =IF(H35<>"",1+MAX($B$15:B34),"") -> 18 | C35: ='DETAILED ESTIMATE'!C1033 -> DIV. 32 | D35: =VLOOKUP($C35,'DETAILED ESTIMATE'!$C$20:$R$1258,2,0) -> EXTERIOR IMPROVEMENT | E35: =VLOOKUP($C35,'DETAILED ESTIMATE'!$C$20:$R$1258,9,0) -> 3077 HRS | F35: =(VLOOKUP($C35,'DETAILED ESTIMATE'!$C$20:$R$1258,7,0))+'DETAILED ESTIMATE'!$Q$7*(VLOOKUP($C35,'DETAILED ESTIMATE'!$C$20:$R$1258,7,0))+'DETAILED ESTIMATE'!$Q$9*(VLOOKUP($C35,'DETAILED ESTIMATE'!$C$20:$R$1258,7,0))+'DETAILED ESTIMATE'!$Q$10*((VLOOKUP($C35,'DETAILED ESTIMATE'!$C$20:$R$1258,7,0))+'DETAILED ESTIMATE'!$Q$7*(VLOOKUP($C35,'DETAILED ESTIMATE'!$C$20:$R$1258,7,0))+'DETAILED ESTIMATE'!$Q$9*(VLOOKUP($C35,'DETAILED ESTIMATE'!$C$20:$R$1258,7,0)))+'DETAILED ESTIMATE'!$Q$11*(VLOOKUP($C35,'DETAILED ESTIMATE'!$C$20:$R$1258,7,0)) -> 302445.07 | G35: =(VLOOKUP($C35,'DETAILED ESTIMATE'!$C$20:$R$1258,14,0))+'DETAILED ESTIMATE'!$Q$8*(VLOOKUP($C35,'DETAILED ESTIMATE'!$C$20:$R$1258,14,0))+'DETAILED ESTIMATE'!$Q$9*(VLOOKUP($C35,'DETAILED ESTIMATE'!$C$20:$R$1258,14,0))+'DETAILED ESTIMATE'!$Q$10*((VLOOKUP($C35,'DETAILED ESTIMATE'!$C$20:$R$1258,14,0))+'DETAILED ESTIMATE'!$Q$8*(VLOOKUP($C35,'DETAILED ESTIMATE'!$C$20:$R$1258,14,0))+'DETAILED ESTIMATE'!$Q$9*(VLOOKUP($C35,'DETAILED ESTIMATE'!$C$20:$R$1258,14,0)))+'DETAILED ESTIMATE'!$Q$11*(VLOOKUP($C35,'DETAILED ESTIMATE'!$C$20:$R$1258,14,0)) -> 168459.86 | H35: =VLOOKUP($C35,'DETAILED ESTIMATE'!$C$20:$R$1258,16,0) -> 470904.93
B36: =IF(H36<>"",1+MAX($B$15:B35),"") -> 19 | C36: ='DETAILED ESTIMATE'!C1221 -> DIV. 33 | D36: =VLOOKUP($C36,'DETAILED ESTIMATE'!$C$20:$R$1258,2,0) -> UTILITIES | E36: =VLOOKUP($C36,'DETAILED ESTIMATE'!$C$20:$R$1258,9,0) -> 1612 HRS | F36: =(VLOOKUP($C36,'DETAILED ESTIMATE'!$C$20:$R$1258,7,0))+'DETAILED ESTIMATE'!$Q$7*(VLOOKUP($C36,'DETAILED ESTIMATE'!$C$20:$R$1258,7,0))+'DETAILED ESTIMATE'!$Q$9*(VLOOKUP($C36,'DETAILED ESTIMATE'!$C$20:$R$1258,7,0))+'DETAILED ESTIMATE'!$Q$10*((VLOOKUP($C36,'DETAILED ESTIMATE'!$C$20:$R$1258,7,0))+'DETAILED ESTIMATE'!$Q$7*(VLOOKUP($C36,'DETAILED ESTIMATE'!$C$20:$R$1258,7,0))+'DETAILED ESTIMATE'!$Q$9*(VLOOKUP($C36,'DETAILED ESTIMATE'!$C$20:$R$1258,7,0)))+'DETAILED ESTIMATE'!$Q$11*(VLOOKUP($C36,'DETAILED ESTIMATE'!$C$20:$R$1258,7,0)) -> 71124.259 | G36: =(VLOOKUP($C36,'DETAILED ESTIMATE'!$C$20:$R$1258,14,0))+'DETAILED ESTIMATE'!$Q$8*(VLOOKUP($C36,'DETAILED ESTIMATE'!$C$20:$R$1258,14,0))+'DETAILED ESTIMATE'!$Q$9*(VLOOKUP($C36,'DETAILED ESTIMATE'!$C$20:$R$1258,14,0))+'DETAILED ESTIMATE'!$Q$10*((VLOOKUP($C36,'DETAILED ESTIMATE'!$C$20:$R$1258,14,0))+'DETAILED ESTIMATE'!$Q$8*(VLOOKUP($C36,'DETAILED ESTIMATE'!$C$20:$R$1258,14,0))+'DETAILED ESTIMATE'!$Q$9*(VLOOKUP($C36,'DETAILED ESTIMATE'!$C$20:$R$1258,14,0)))+'DETAILED ESTIMATE'!$Q$11*(VLOOKUP($C36,'DETAILED ESTIMATE'!$C$20:$R$1258,14,0)) -> 76562.623 | H36: =VLOOKUP($C36,'DETAILED ESTIMATE'!$C$20:$R$1258,16,0) -> 147686.88
B37: =IF(H37<>"",1+MAX($B$15:B36),"")
B38: =IF(H38<>"",1+MAX($B$15:B37),"") -> 20 | D38: TOTAL PROJECT COST AND MANHOURS | E38: =ROUNDUP('DETAILED ESTIMATE'!R13,0) & " " & "HRS" -> 13369 HRS | H38: =SUM(H18:H37) -> 2194319.3
B39: =IF(H39<>"",1+MAX($B$15:B38),"")

Sheet DETAILED ESTIMATE
T1: MAT. FAC. | U1: LAB. FAC.
B2: CONSTRUCTION COST ESTIMATE BREAKDOWN | T2: 0.952 | U2: 0.731
J3: PROPOSED PROJECT AMOUNT
J4: TOTAL MATERIAL COST | R4: =SUM(I20:I1258)/2 -> 907334.95
J5: TOTAL LABOR COST | R5: =SUM(P20:P1258)/2 -> 649836.58
J6: SUBTOTAL | R6: =SUM(R4:R5) -> 1557171.5
J7: SALES TAX | Q7: 0.07 | R7: =R4*Q7 -> 63513.447
J8: LABOR BURDEN | Q8: 0.1 | R8: =R5*Q8 -> 64983.658
J9: OVERHEAD & PROFIT | Q9: 0.25 | R9: =R6*Q9 -> 389292.88
J10: BONDING | Q10: 0.02 | R10: =SUM(R6:R9)*Q10 -> 41499.23
J11: CONTINGENCY / WASTAGE | Q11: 0.05 | R11: =R6*Q11 -> 77858.577
J12: PROPOSED PROJECT AMOUNT | R12: =SUM(R6:R11) -> 2194319.3
J13: TOTAL MANHOURS | R13: =SUM(K21:K1258) -> 13368.127
B14: DATE | D14: SCOPE OF WORK | E14: PROJECT NAME | J14: PROJECT LOCATION
B15: 46304 | D15: COMPLETE GC | E15: FIFTH THIRD BANK WATSON BLVD | J15: 2711 WATSON BOULEVARD WARNER ROBINS, GA 31093
E16: GROSS AREA: 2000 SF
B17: LINE NO. | C17: DWG REF./ CSI SEC. | D17: ITEM DESCRIPTION | E17: UNIT OF MEASURE | F17: QUANTITY | G17: MATERIAL | J17: LABOR | Q17: LINE TOTAL | R17: TRADE TOTAL W/ S.TAX, O&P
G18: UNIT PRICE | H18: UNIT PRICE | I18: TOTAL COST | J18: UNIT LABOR HOUR | K18: LABOR HOURS | L18: CREW | M18: LABOR RATE | N18: LABOR RATE | O18: UNIT PRICE | P18: TOTAL COST
B19: =IF(F19<>"",1+MAX($B$1:B18),"")
B20: =IF(F20<>"",1+MAX($B$1:B19),"") | C20: DIV. 01 | D20: GENERAL REQUIREMENTS | H20: SUBTOTAL MATERIAL | I20: =SUM(I21:I23) -> 0 | J20: SUBTOTAL LAB. HRS. | K20: =ROUND(SUM(K21:K23),0) & " " & "HRS" -> 0 HRS | O20: SUBTOTAL LABOR | P20: =SUM(P21:P23) -> 115500 | Q20: =SUM(Q21:Q23) -> 115500 | R20: =(Q20)+(I20*$Q$7)+(P20*$Q$8)+(Q20*$Q$9)+($Q$10*((Q20)+(I20*$Q$7)+(P20*$Q$8)+(Q20*$Q$9)))+(Q20*$Q$11) -> 164818.5
H21: =G21*$T$2 -> 0 | I21: =F21*H21 -> 0 | K21: =F21*J21 -> 0 | N21: =M21*$U$2 -> 0 | O21: =J21*N21 -> 0 | P21: =F21*O21 -> 0 | Q21: =I21+P21 -> 0 | R21: =Q21+(I21*$Q$7)+(P21*$Q$8)+(Q21*$Q$9)+(Q21*$Q$11)+($Q$10*(Q21+(I21*$Q$7)+(P21*$Q$8)+(Q21*$Q$9))) -> 0
B22: =IF(F22<>"",1+MAX($B$21:B21),"") -> 1 | D22: PERMITS, SITE SUPERVISION, FINAL CLEANUP & DUMPSTER | E22: LS | F22: 1 | H22: =G22*$T$2 -> 0 | I22: =F22*H22 -> 0 | K22: =F22*J22 -> 0 | N22: =M22*$U$2 -> 0 | O22: 115500 | P22: =F22*O22 -> 115500 | Q22: =I22+P22 -> 115500 | R22: =Q22+(I22*$Q$7)+(P22*$Q$8)+(Q22*$Q$9)+(Q22*$Q$11)+($Q$10*(Q22+(I22*$Q$7)+(P22*$Q$8)+(Q22*$Q$9))) -> 164818.5
B23: =IF(F23<>"",1+MAX($B$21:B22),"") | H23: =G23*$T$2 -> 0 | I23: =F23*H23 -> 0 | K23: =F23*J23 -> 0 | N23: =M23*$U$2 -> 0 | O23: =J23*N23 -> 0 | P23: =F23*O23 -> 0 | Q23: =I23+P23 -> 0 | R23: =Q23+(I23*$Q$7)+(P23*$Q$8)+(Q23*$Q$9)+(Q23*$Q$11)+($Q$10*(Q23+(I23*$Q$7)+(P23*$Q$8)+(Q23*$Q$9))) -> 0
B24: =IF(F24<>"",1+MAX($B$21:B23),"") | C24: DIV. 02 | D24: EXISTING CONDITIONS | H24: SUBTOTAL MATERIAL | I24: =SUM(I25:I40) -> 0 | J24: SUBTOTAL LAB. HRS. | K24: =ROUND(SUM(K25:K40),0) & " " & "HRS" -> 2747 HRS | O24: SUBTOTAL LABOR | P24: =SUM(P25:P40) -> 121063.61 | Q24: =SUM(Q25:Q40) -> 121063.61 | R24: =(Q24)+(I24*$Q$7)+(P24*$Q$8)+(Q24*$Q$9)+($Q$10*((Q24)+(I24*$Q$7)+(P24*$Q$8)+(Q24*$Q$9)))+(Q24*$Q$11) -> 172757.77
B25: =IF(F25<>"",1+MAX($B$21:B24),"") | H25: =G25*$T$2 -> 0 | I25: =F25*H25 -> 0 | K25: =F25*J25 -> 0 | N25: =M25*$U$2 -> 0 | O25: =J25*N25 -> 0 | P25: =F25*O25 -> 0 | Q25: =I25+P25 -> 0 | R25: =Q25+(I25*$Q$7)+(P25*$Q$8)+(Q25*$Q$9)+(Q25*$Q$11)+($Q$10*(Q25+(I25*$Q$7)+(P25*$Q$8)+(Q25*$Q$9))) -> 0
B26: =IF(F26<>"",1+MAX($B$21:B25),"") | D26: DEMOLITION | H26: =G26*$T$2 -> 0 | I26: =F26*H26 -> 0 | K26: =F26*J26 -> 0 | N26: =M26*$U$2 -> 0 | O26: =J26*N26 -> 0 | P26: =F26*O26 -> 0 | Q26: =I26+P26 -> 0 | R26: =Q26+(I26*$Q$7)+(P26*$Q$8)+(Q26*$Q$9)+(Q26*$Q$11)+($Q$10*(Q26+(I26*$Q$7)+(P26*$Q$8)+(Q26*$Q$9))) -> 0
B27: =IF(F27<>"",1+MAX($B$21:B26),"") -> 2 | C27: C-1.0 | D27: 1: REMOVE EXISTING CURB & GUTTER | E27: LF | F27: 987.22 | H27: =G27*$T$2 -> 0 | I27: =F27*H27 -> 0 | J27: 0.165 | K27: =F27*J27 -> 162.8913 | L27: 1 CLAB | M27: 42.1 | N27: =M27*$U$2 -> 30.7751 | O27: =J27*N27 -> 5.0778915 | P27: =F27*O27 -> 5012.996 | Q27: =I27+P27 -> 5012.996 | R27: =Q27+(I27*$Q$7)+(P27*$Q$8)+(Q27*$Q$9)+(Q27*$Q$11)+($Q$10*(Q27+(I27*$Q$7)+(P27*$Q$8)+(Q27*$Q$9))) -> 7153.5454
B28: =IF(F28<>"",1+MAX($B$21:B27),"") -> 3 | D28: 2: REMOVE EXISTING TWO STORY BUILDING STRUCTURE AND FOUNDATION | E28: CFT | F28: =4489*20 -> 89780 | H28: =G28*$T$2 -> 0 | I28: =F28*H28 -> 0 | J28: 0.009 | K28: =F28*J28 -> 808.02 | L28: B-8 | M28: 94.03 | N28: =M28*$U$2 -> 68.73593 | O28: =J28*N28 -> 0.61862337 | P28: =F28*O28 -> 55540.006 | Q28: =I28+P28 -> 55540.006 | R28: =Q28+(I28*$Q$7)+(P28*$Q$8)+(Q28*$Q$9)+(Q28*$Q$11)+($Q$10*(Q28+(I28*$Q$7)+(P28*$Q$8)+(Q28*$Q$9))) -> 79255.589
B29: =IF(F29<>"",1+MAX($B$21:B28),"") -> 4 | D29: 2: REMOVE EXISTING ONE STORY BUILDING STRUCTURE AND FOUNDATION | E29: CFT | F29: =1714*10 -> 17140 | H29: =G29*$T$2 -> 0 | I29: =F29*H29 -> 0 | J29: 0.009 | K29: =F29*J29 -> 154.26 | L29: B-8 | M29: 94.03 | N29: =M29*$U$2 -> 68.73593 | O29: =J29*N29 -> 0.61862337 | P29: =F29*O29 -> 10603.205 | Q29: =I29+P29 -> 10603.205 | R29: =Q29+(I29*$Q$7)+(P29*$Q$8)+(Q29*$Q$9)+(Q29*$Q$11)+($Q$10*(Q29+(I29*$Q$7)+(P29*$Q$8)+(Q29*$Q$9))) -> 15130.773
B30: =IF(F30<>"",1+MAX($B$21:B29),"") -> 5 | D30: 9: REMOVE EXISTING SIDEWALK | E30: SF | F30: 390.17 | H30: =G30*$T$2 -> 0 | I30: =F30*H30 -> 0 | J30: 0.075 | K30: =F30*J30 -> 29.26275 | L30: 1 CLAB | M30: 42.1 | N30: =M30*$U$2 -> 30.7751 | O30: =J30*N30 -> 2.3081325 | P30: =F30*O30 -> 900.56406 | Q30: =I30+P30 -> 900.56406 | R30: =Q30+(I30*$Q$7)+(P30*$Q$8)+(Q30*$Q$9)+(Q30*$Q$11)+($Q$10*(Q30+(I30*$Q$7)+(P30*$Q$8)+(Q30*$Q$9))) -> 1285.1049
B31: =IF(F31<>"",1+MAX($B$21:B30),"") -> 6 | D31: 10: REMOVE EXISTING MONUMENT SIGN | E31: EA | F31: 1 | H31: =G31*$T$2 -> 0 | I31: =F31*H31 -> 0 | J31: 3.5 | K31: =F31*J31 -> 3.5 | L31: 1 CLAB | M31: 42.1 | N31: =M31*$U$2 -> 30.7751 | O31: =J31*N31 -> 107.71285 | P31: =F31*O31 -> 107.71285 | Q31: =I31+P31 -> 107.71285 | R31: =Q31+(I31*$Q$7)+(P31*$Q$8)+(Q31*$Q$9)+(Q31*$Q$11)+($Q$10*(Q31+(I31*$Q$7)+(P31*$Q$8)+(Q31*$Q$9))) -> 153.70624
B32: =IF(F32<>"",1+MAX($B$21:B31),"") -> 7 | D32: 11: REMOVE EXISTING CONCRETE RAMP | E32: SF | F32: 442.37 | H32: =G32*$T$2 -> 0 | I32: =F32*H32 -> 0 | J32: 0.075 | K32: =F32*J32 -> 33.17775 | L32: 1 CLAB | M32: 42.1 | N32: =M32*$U$2 -> 30.7751 | O32: =J32*N32 -> 2.3081325 | P32: =F32*O32 -> 1021.0486 | Q32: =I32+P32 -> 1021.0486 | R32: =Q32+(I32*$Q$7)+(P32*$Q$8)+(Q32*$Q$9)+(Q32*$Q$11)+($Q$10*(Q32+(I32*$Q$7)+(P32*$Q$8)+(Q32*$Q$9))) -> 1457.0363
B33: =IF(F33<>"",1+MAX($B$21:B32),"") -> 8 | D33: 11: REMOVE EXISTING BRICK STAIR STEPS | E33: EA | F33: 7 | H33: =G33*$T$2 -> 0 | I33: =F33*H33 -> 0 | J33: 0.225 | K33: =F33*J33 -> 1.575 | L33: 1 CLAB | M33: 42.1 | N33: =M33*$U$2 -> 30.7751 | O33: =J33*N33 -> 6.9243975 | P33: =F33*O33 -> 48.470783 | Q33: =I33+P33 -> 48.470783 | R33: =Q33+(I33*$Q$7)+(P33*$Q$8)+(Q33*$Q$9)+(Q33*$Q$11)+($Q$10*(Q33+(I33*$Q$7)+(P33*$Q$8)+(Q33*$Q$9))) -> 69.167807
B34: =IF(F34<>"",1+MAX($B$21:B33),"") -> 9 | D34: 7: REMOVE EXISTING PAVEMENT W/ PAVEMENT STRIPING | E34: SF | F34: 19363.57 | H34: =G34*$T$2 -> 0 | I34: =F34*H34 -> 0 | J34: 0.075 | K34: =F34*J34 -> 1452.2677 | L34: 1 CLAB | M34: 42.1 | N34: =M34*$U$2 -> 30.7751 | O34: =J34*N34 -> 2.3081325 | P34: =F34*O34 -> 44693.685 | Q34: =I34+P34 -> 44693.685 | R34: =Q34+(I34*$Q$7)+(P34*$Q$8)+(Q34*$Q$9)+(Q34*$Q$11)+($Q$10*(Q34+(I34*$Q$7)+(P34*$Q$8)+(Q34*$Q$9))) -> 63777.889
B35: =IF(F35<>"",1+MAX($B$21:B34),"") -> 10 | D35: 8: REMOVE EXISTING TREES/VEGETATION | E35: EA | F35: 2 | H35: =G35*$T$2 -> 0 | I35: =F35*H35 -> 0 | J35: 1.95 | K35: =F35*J35 -> 3.9 | L35: 1 CLAB | M35: 42.1 | N35: =M35*$U$2 -> 30.7751 | O35: =J35*N35 -> 60.011445 | P35: =F35*O35 -> 120.02289 | Q35: =I35+P35 -> 120.02289 | R35: =Q35+(I35*$Q$7)+(P35*$Q$8)+(Q35*$Q$9)+(Q35*$Q$11)+($Q$10*(Q35+(I35*$Q$7)+(P35*$Q$8)+(Q35*$Q$9))) -> 171.27266
B36: =IF(F36<>"",1+MAX($B$21:B35),"") -> 11 | D36: 6: REMOVE EXISTING WATER LINE AND ASSOCIATED STRUCTURES | E36: LF | F36: 55.6 | H36: =G36*$T$2 -> 0 | I36: =F36*H36 -> 0 | J36: 0.065 | K36: =F36*J36 -> 3.614 | L36: 1 CLAB | M36: 42.1 | N36: =M36*$U$2 -> 30.7751 | O36: =J36*N36 -> 2.0003815 | P36: =F36*O36 -> 111.22121 | Q36: =I36+P36 -> 111.22121 | R36: =Q36+(I36*$Q$7)+(P36*$Q$8)+(Q36*$Q$9)+(Q36*$Q$11)+($Q$10*(Q36+(I36*$Q$7)+(P36*$Q$8)+(Q36*$Q$9))) -> 158.71267
B37: =IF(F37<>"",1+MAX($B$21:B36),"") -> 12 | D37: 5: REMOVE EXISTING POWER LINE AND ASSOCIATED STRUCTURES | E37: LF | F37: 965.36 | H37: =G37*$T$2 -> 0 | I37: =F37*H37 -> 0 | J37: 0.06 | K37: =F37*J37 -> 57.9216 | L37: 1 CLAB | M37: 42.1 | N37: =M37*$U$2 -> 30.7751 | O37: =J37*N37 -> 1.846506 | P37: =F37*O37 -> 1782.543 | Q37: =I37+P37 -> 1782.543 | R37: =Q37+(I37*$Q$7)+(P37*$Q$8)+(Q37*$Q$9)+(Q37*$Q$11)+($Q$10*(Q37+(I37*$Q$7)+(P37*$Q$8)+(Q37*$Q$9))) -> 2543.6889
B38: =IF(F38<>"",1+MAX($B$21:B37),"") -> 13 | D38: REMOVE EXISTING METAL HANDRAIL | E38: LF | F38: 76.2 | H38: =G38*$T$2 -> 0 | I38: =F38*H38 -> 0 | J38: 0.135 | K38: =F38*J38 -> 10.287 | L38: 1 CLAB | M38: 42.1 | N38: =M38*$U$2 -> 30.7751 | O38: =J38*N38 -> 4.1546385 | P38: =F38*O38 -> 316.58345 | Q38: =I38+P38 -> 316.58345 | R38: =Q38+(I38*$Q$7)+(P38*$Q$8)+(Q38*$Q$9)+(Q38*$Q$11)+($Q$10*(Q38+(I38*$Q$7)+(P38*$Q$8)+(Q38*$Q$9))) -> 451.76459
B39: =IF(F39<>"",1+MAX($B$21:B38),"") -> 14 | D39: 4: REMOVE EXISTING STORM SEWER LINE AND ASSOCIATED STRUCTURES - ASSUMED | E39: LF | F39: 107.11 | H39: =G39*$T$2 -> 0 | I39: =F39*H39 -> 0 | J39: 0.095 | K39: =F39*J39 -> 10.17545 | L39: 1 CLAB | M39: 42.1 | N39: =M39*$U$2 -> 30.7751 | O39: =J39*N39 -> 2.9236345 | P39: =F39*O39 -> 313.15049 | Q39: =I39+P39 -> 313.15049 | R39: =Q39+(I39*$Q$7)+(P39*$Q$8)+(Q39*$Q$9)+(Q39*$Q$11)+($Q$10*(Q39+(I39*$Q$7)+(P39*$Q$8)+(Q39*$Q$9))) -> 446.86575
B40: =IF(F40<>"",1+MAX($B$21:B39),"") -> 15 | D40: 4: REMOVE EXISTING STORM STRUCTURE | E40: EA | F40: 2 | H40: =G40*$T$2 -> 0 | I40: =F40*H40 -> 0 | J40: 8 | K40: =F40*J40 -> 16 | L40: 1 CLAB | M40: 42.1 | N40: =M40*$U$2 -> 30.7751 | O40: =J40*N40 -> 246.2008 | P40: =F40*O40 -> 492.4016 | Q40: =I40+P40 -> 492.4016 | R40: =Q40+(I40*$Q$7)+(P40*$Q$8)+(Q40*$Q$9)+(Q40*$Q$11)+($Q$10*(Q40+(I40*$Q$7)+(P40*$Q$8)+(Q40*$Q$9))) -> 702.65708
B41: =IF(F41<>"",1+MAX($B$21:B40),"") | H41: =G41*$T$2 -> 0 | I41: =F41*H41 -> 0 | K41: =F41*J41 -> 0 | N41: =M41*$U$2 -> 0 | O41: =J41*N41 -> 0 | P41: =F41*O41 -> 0 | Q41: =I41+P41 -> 0 | R41: =Q41+(I41*$Q$7)+(P41*$Q$8)+(Q41*$Q$9)+(Q41*$Q$11)+($Q$10*(Q41+(I41*$Q$7)+(P41*$Q$8)+(Q41*$Q$9))) -> 0
B42: =IF(F42<>"",1+MAX($B$21:B23),"") | C42: DIV. 03 | D42: CONCRETE | H42: SUBTOTAL MATERIAL | I42: =SUM(I43:I74) -> 19139.258 | K42: =ROUND(SUM(K43:K74),0) & " " & "HRS" -> 413 HRS | O42: SUBTOTAL LABOR | P42: =SUM(P43:P74) -> 15358.706 | Q42: =SUM(Q43:Q74) -> 34497.964 | R42: =(Q42)+(I42*$Q$7)+(P42*$Q$8)+(Q42*$Q$9)+($Q$10*((Q42)+(I42*$Q$7)+(P42*$Q$8)+(Q42*$Q$9)))+(Q42*$Q$11) -> 48642.933
B43: =IF(F43<>"",1+MAX($B$21:B42),"") | H43: =G43*$T$2 -> 0 | I43: =F43*H43 -> 0 | K43: =F43*J43 -> 0 | N43: =M43*$U$2 -> 0 | O43: =J43*N43 -> 0 | P43: =F43*O43 -> 0 | Q43: =I43+P43 -> 0 | R43: =Q43+(I43*$Q$7)+(P43*$Q$8)+(Q43*$Q$9)+(Q43*$Q$11)+($Q$10*(Q43+(I43*$Q$7)+(P43*$Q$8)+(Q43*$Q$9))) -> 0
B44: =IF(F44<>"",1+MAX($B$21:B43),"") | D44: SLAB ON GRADE | H44: =G44*$T$2 -> 0 | I44: =F44*H44 -> 0 | K44: =F44*J44 -> 0 | N44: =M44*$U$2 -> 0 | O44: =J44*N44 -> 0 | P44: =F44*O44 -> 0 | Q44: =I44+P44 -> 0 | R44: =Q44+(I44*$Q$7)+(P44*$Q$8)+(Q44*$Q$9)+(Q44*$Q$11)+($Q$10*(Q44+(I44*$Q$7)+(P44*$Q$8)+(Q44*$Q$9))) -> 0
B45: =IF(F45<>"",1+MAX($B$21:B44),"") -> 16 | C45: S201 | D45: 4"THK. CONCRETE SLAB ON GRADE W/ 6x6 W2.9xW2.9 WIRE MESH O/ 10 MIL VAPOR BARRIER O/ 4"THK. GRAVEL BED | E45: SF | F45: 1917.6 | G45: 2.59 | H45: =G45*$T$2 -> 2.46568 | I45: =F45*H45 -> 4728.188 | J45: 0.073 | K45: =F45*J45 -> 139.9848 | L45: C14G | M45: 47.35 | N45: =M45*$U$2 -> 34.61285 | O45: =J45*N45 -> 2.5267381 | P45: =F45*O45 -> 4845.2729 | Q45: =I45+P45 -> 9573.4609 | R45: =Q45+(I45*$Q$7)+(P45*$Q$8)+(Q45*$Q$9)+(Q45*$Q$11)+($Q$10*(Q45+(I45*$Q$7)+(P45*$Q$8)+(Q45*$Q$9))) -> 13516.646
B46: =IF(F46<>"",1+MAX($B$21:B45),"") | H46: =G46*$T$2 -> 0 | I46: =F46*H46 -> 0 | K46: =F46*J46 -> 0 | N46: =M46*$U$2 -> 0 | O46: =J46*N46 -> 0 | P46: =F46*O46 -> 0 | Q46: =I46+P46 -> 0 | R46: =Q46+(I46*$Q$7)+(P46*$Q$8)+(Q46*$Q$9)+(Q46*$Q$11)+($Q$10*(Q46+(I46*$Q$7)+(P46*$Q$8)+(Q46*$Q$9))) -> 0
B47: =IF(F47<>"",1+MAX($B$21:B46),"") | D47: JOINT | H47: =G47*$T$2 -> 0 | I47: =F47*H47 -> 0 | K47: =F47*J47 -> 0 | N47: =M47*$U$2 -> 0 | O47: =J47*N47 -> 0 | P47: =F47*O47 -> 0 | Q47: =I47+P47 -> 0 | R47: =Q47+(I47*$Q$7)+(P47*$Q$8)+(Q47*$Q$9)+(Q47*$Q$11)+($Q$10*(Q47+(I47*$Q$7)+(P47*$Q$8)+(Q47*$Q$9))) -> 0
B48: =IF(F48<>"",1+MAX($B$21:B47),"") -> 17 | D48: 1/2" ISOLATION JOINT | E48: LF | F48: 39.22 | G48: 1.29 | H48: =G48*$T$2 -> 1.22808 | I48: =F48*H48 -> 48.165298 | J48: 0.024 | K48: =F48*J48 -> 0.94128 | L48: 1 CARP | M48: 53.15 | N48: =M48*$U$2 -> 38.85265 | O48: =J48*N48 -> 0.9324636 | P48: =F48*O48 -> 36.571222 | Q48: =I48+P48 -> 84.73652 | R48: =Q48+(I48*$Q$7)+(P48*$Q$8)+(Q48*$Q$9)+(Q48*$Q$11)+($Q$10*(Q48+(I48*$Q$7)+(P48*$Q$8)+(Q48*$Q$9))) -> 119.44516
B49: =IF(F49<>"",1+MAX($B$21:B48),"") -> 18 | D49: 1" SAW-CUT JOINT | E49: LF | F49: 364.11 | G49: 1.59 | H49: =G49*$T$2 -> 1.51368 | I49: =F49*H49 -> 551.14602 | J49: 0.024 | K49: =F49*J49 -> 8.73864 | L49: 1 CARP | M49: 53.15 | N49: =M49*$U$2 -> 38.85265 | O49: =J49*N49 -> 0.9324636 | P49: =F49*O49 -> 339.51932 | Q49: =I49+P49 -> 890.66535 | R49: =Q49+(I49*$Q$7)+(P49*$Q$8)+(Q49*$Q$9)+(Q49*$Q$11)+($Q$10*(Q49+(I49*$Q$7)+(P49*$Q$8)+(Q49*$Q$9))) -> 1254.1144
B50: =IF(F50<>"",1+MAX($B$21:B49),"") | H50: =G50*$T$2 -> 0 | I50: =F50*H50 -> 0 | K50: =F50*J50 -> 0 | N50: =M50*$U$2 -> 0 | O50: =J50*N50 -> 0 | P50: =F50*O50 -> 0 | Q50: =I50+P50 -> 0 | R50: =Q50+(I50*$Q$7)+(P50*$Q$8)+(Q50*$Q$9)+(Q50*$Q$11)+($Q$10*(Q50+(I50*$Q$7)+(P50*$Q$8)+(Q50*$Q$9))) -> 0
B51: =IF(F51<>"",1+MAX($B$21:B50),"") | D51: FOOTING | H51: =G51*$T$2 -> 0 | I51: =F51*H51 -> 0 | K51: =F51*J51 -> 0 | N51: =M51*$U$2 -> 0 | O51: =J51*N51 -> 0 | P51: =F51*O51 -> 0 | Q51: =I51+P51 -> 0 | R51: =Q51+(I51*$Q$7)+(P51*$Q$8)+(Q51*$Q$9)+(Q51*$Q$11)+($Q$10*(Q51+(I51*$Q$7)+(P51*$Q$8)+(Q51*$Q$9))) -> 0
B52: =IF(F52<>"",1+MAX($B$21:B51),"") | H52: =G52*$T$2 -> 0 | I52: =F52*H52 -> 0 | K52: =F52*J52 -> 0 | N52: =M52*$U$2 -> 0 | O52: =J52*N52 -> 0 | P52: =F52*O52 -> 0 | Q52: =I52+P52 -> 0 | R52: =Q52+(I52*$Q$7)+(P52*$Q$8)+(Q52*$Q$9)+(Q52*$Q$11)+($Q$10*(Q52+(I52*$Q$7)+(P52*$Q$8)+(Q52*$Q$9))) -> 0
B53: =IF(F53<>"",1+MAX($B$21:B52),"") | C53: S201 | D53: CONTINUOUS FOOTING | H53: =G53*$T$2 -> 0 | I53: =F53*H53 -> 0 | K53: =F53*J53 -> 0 | N53: =M53*$U$2 -> 0 | O53: =J53*N53 -> 0 | P53: =F53*O53 -> 0 | Q53: =I53+P53 -> 0 | R53: =Q53+(I53*$Q$7)+(P53*$Q$8)+(Q53*$Q$9)+(Q53*$Q$11)+($Q$10*(Q53+(I53*$Q$7)+(P53*$Q$8)+(Q53*$Q$9))) -> 0
B54: =IF(F54<>"",1+MAX($B$21:B53),"") -> 19 | D54: 2'Wx1'D CONTINUOUS FOOTING W/ (2) #6 BARS | E54: CY | F54: =124.15*2*1/27 -> 9.1962963 | G54: 310 | H54: =G54*$T$2 -> 295.12 | I54: =F54*H54 -> 2714.011 | J54: 5.73 | K54: =F54*J54 -> 52.694778 | L54: C14C | M54: 50.61 | N54: =M54*$U$2 -> 36.99591 | O54: =J54*N54 -> 211.98656 | P54: =F54*O54 -> 1949.4913 | Q54: =I54+P54 -> 4663.5022 | R54: =Q54+(I54*$Q$7)+(P54*$Q$8)+(Q54*$Q$9)+(Q54*$Q$11)+($Q$10*(Q54+(I54*$Q$7)+(P54*$Q$8)+(Q54*$Q$9))) -> 6571.7689
B55: =IF(F55<>"",1+MAX($B$21:B54),"") | H55: =G55*$T$2 -> 0 | I55: =F55*H55 -> 0 | K55: =F55*J55 -> 0 | N55: =M55*$U$2 -> 0 | O55: =J55*N55 -> 0 | P55: =F55*O55 -> 0 | Q55: =I55+P55 -> 0 | R55: =Q55+(I55*$Q$7)+(P55*$Q$8)+(Q55*$Q$9)+(Q55*$Q$11)+($Q$10*(Q55+(I55*$Q$7)+(P55*$Q$8)+(Q55*$Q$9))) -> 0
B56: =IF(F56<>"",1+MAX($B$21:B55),"") | D56: ISOLATED FOOTING | H56: =G56*$T$2 -> 0 | I56: =F56*H56 -> 0 | K56: =F56*J56 -> 0 | N56: =M56*$U$2 -> 0 | O56: =J56*N56 -> 0 | P56: =F56*O56 -> 0 | Q56: =I56+P56 -> 0 | R56: =Q56+(I56*$Q$7)+(P56*$Q$8)+(Q56*$Q$9)+(Q56*$Q$11)+($Q$10*(Q56+(I56*$Q$7)+(P56*$Q$8)+(Q56*$Q$9))) -> 0
B57: =IF(F57<>"",1+MAX($B$21:B56),"") -> 20 | D57: 3'x3'x1'D ISOLATED FOOTING W/ (4) #4 EACHWAY BARS | E57: CY | F57: =3*3*1*3/27 -> 1 | G57: 304.22 | H57: =G57*$T$2 -> 289.61744 | I57: =F57*H57 -> 289.61744 | J57: 6.415 | K57: =F57*J57 -> 6.415 | L57: C14H | M57: 52.21 | N57: =M57*$U$2 -> 38.16551 | O57: =J57*N57 -> 244.83175 | P57: =F57*O57 -> 244.83175 | Q57: =I57+P57 -> 534.44919 | R57: =Q57+(I57*$Q$7)+(P57*$Q$8)+(Q57*$Q$9)+(Q57*$Q$11)+($Q$10*(Q57+(I57*$Q$7)+(P57*$Q$8)+(Q57*$Q$9))) -> 753.7967
B58: =IF(F58<>"",1+MAX($B$21:B57),"") -> 21 | D58: 3'8"x3'8"x1'D ISOLATED FOOTING W/ (5) #4 EACHWAY BARS | E58: CY | F58: =3.67*3.67*1*3/27 -> 1.4965444 | G58: 304.22 | H58: =G58*$T$2 -> 289.61744 | I58: =F58*H58 -> 433.42537 | J58: 6.415 | K58: =F58*J58 -> 9.6003326 | L58: C14H | M58: 52.21 | N58: =M58*$U$2 -> 38.16551 | O58: =J58*N58 -> 244.83175 | P58: =F58*O58 -> 366.40159 | Q58: =I58+P58 -> 799.82696 | R58: =Q58+(I58*$Q$7)+(P58*$Q$8)+(Q58*$Q$9)+(Q58*$Q$11)+($Q$10*(Q58+(I58*$Q$7)+(P58*$Q$8)+(Q58*$Q$9))) -> 1128.0903
B59: =IF(F59<>"",1+MAX($B$21:B58),"") -> 22 | D59: 5'x5'x1'2"D ISOLATED FOOTING W/ (5) #5 EACHWAY BARS | E59: CY | F59: =5*5*1.17*6/27 -> 6.5 | G59: 304.22 | H59: =G59*$T$2 -> 289.61744 | I59: =F59*H59 -> 1882.5134 | J59: 6.415 | K59: =F59*J59 -> 41.6975 | L59: C14H | M59: 52.21 | N59: =M59*$U$2 -> 38.16551 | O59: =J59*N59 -> 244.83175 | P59: =F59*O59 -> 1591.4064 | Q59: =I59+P59 -> 3473.9197 | R59: =Q59+(I59*$Q$7)+(P59*$Q$8)+(Q59*$Q$9)+(Q59*$Q$11)+($Q$10*(Q59+(I59*$Q$7)+(P59*$Q$8)+(Q59*$Q$9))) -> 4899.6785
B60: =IF(F60<>"",1+MAX($B$21:B59),"") -> 23 | D60: 6'x6'x1'4"D ISOLATED FOOTING W/ (7) #5 EACHWAY BARS | E60: CY | F60: =6*6*1.33*1/27 -> 1.7733333 | G60: 304.22 | H60: =G60*$T$2 -> 289.61744 | I60: =F60*H60 -> 513.58826 | J60: 6.415 | K60: =F60*J60 -> 11.375933 | L60: C14H | M60: 52.21 | N60: =M60*$U$2 -> 38.16551 | O60: =J60*N60 -> 244.83175 | P60: =F60*O60 -> 434.1683 | Q60: =I60+P60 -> 947.75656 | R60: =Q60+(I60*$Q$7)+(P60*$Q$8)+(Q60*$Q$9)+(Q60*$Q$11)+($Q$10*(Q60+(I60*$Q$7)+(P60*$Q$8)+(Q60*$Q$9))) -> 1336.7328
B61: =IF(F61<>"",1+MAX($B$21:B60),"") -> 24 | D61: 7'x7'x1'4"D ISOLATED FOOTING W/ (7) #6 EACHWAY BARS | E61: CY | F61: =7*7*1.33*1/27 -> 2.4137037 | G61: 304.22 | H61: =G61*$T$2 -> 289.61744 | I61: =F61*H61 -> 699.05069 | J61: 6.415 | K61: =F61*J61 -> 15.483909 | L61: C14H | M61: 52.21 | N61: =M61*$U$2 -> 38.16551 | O61: =J61*N61 -> 244.83175 | P61: =F61*O61 -> 590.95129 | Q61: =I61+P61 -> 1290.002 | R61: =Q61+(I61*$Q$7)+(P61*$Q$8)+(Q61*$Q$9)+(Q61*$Q$11)+($Q$10*(Q61+(I61*$Q$7)+(P61*$Q$8)+(Q61*$Q$9))) -> 1819.4419
B62: =IF(F62<>"",1+MAX($B$21:B61),"") -> 25 | D62: 7'x4'x1'4"D ISOLATED FOOTING W/ (7) #6 TOP & BOTTOM BARS, (5) #6 TOP & BOTTOM BARS | E62: CY | F62: =7*4*1.33*1/27 -> 1.3792593 | G62: 304.22 | H62: =G62*$T$2 -> 289.61744 | I62: =F62*H62 -> 399.45754 | J62: 6.415 | K62: =F62*J62 -> 8.8479481 | L62: C14H | M62: 52.21 | N62: =M62*$U$2 -> 38.16551 | O62: =J62*N62 -> 244.83175 | P62: =F62*O62 -> 337.68645 | Q62: =I62+P62 -> 737.14399 | R62: =Q62+(I62*$Q$7)+(P62*$Q$8)+(Q62*$Q$9)+(Q62*$Q$11)+($Q$10*(Q62+(I62*$Q$7)+(P62*$Q$8)+(Q62*$Q$9))) -> 1039.6811
B63: =IF(F63<>"",1+MAX($B$21:B62),"") -> 26 | D63: 5'x10'x1'2"D ISOLATED FOOTING W/ (9) #6 TOP & BOTTOM BARS, (5) #6 TOP & BOTTOM BARS | E63: CY | F63: =5*10*1.17*1/27 -> 2.1666667 | G63: 304.22 | H63: =G63*$T$2 -> 289.61744 | I63: =F63*H63 -> 627.50445 | J63: 6.415 | K63: =F63*J63 -> 13.899167 | L63: C14H | M63: 52.21 | N63: =M63*$U$2 -> 38.16551 | O63: =J63*N63 -> 244.83175 | P63: =F63*O63 -> 530.46878 | Q63: =I63+P63 -> 1157.9732 | R63: =Q63+(I63*$Q$7)+(P63*$Q$8)+(Q63*$Q$9)+(Q63*$Q$11)+($Q$10*(Q63+(I63*$Q$7)+(P63*$Q$8)+(Q63*$Q$9))) -> 1633.2262
B64: =IF(F64<>"",1+MAX($B$21:B63),"") | H64: =G64*$T$2 -> 0 | I64: =F64*H64 -> 0 | K64: =F64*J64 -> 0 | N64: =M64*$U$2 -> 0 | O64: =J64*N64 -> 0 | P64: =F64*O64 -> 0 | Q64: =I64+P64 -> 0 | R64: =Q64+(I64*$Q$7)+(P64*$Q$8)+(Q64*$Q$9)+(Q64*$Q$11)+($Q$10*(Q64+(I64*$Q$7)+(P64*$Q$8)+(Q64*$Q$9))) -> 0
B65: =IF(F65<>"",1+MAX($B$21:B64),"") | D65: STEM WALL | H65: =G65*$T$2 -> 0 | I65: =F65*H65 -> 0 | K65: =F65*J65 -> 0 | N65: =M65*$U$2 -> 0 | O65: =J65*N65 -> 0 | P65: =F65*O65 -> 0 | Q65: =I65+P65 -> 0 | R65: =Q65+(I65*$Q$7)+(P65*$Q$8)+(Q65*$Q$9)+(Q65*$Q$11)+($Q$10*(Q65+(I65*$Q$7)+(P65*$Q$8)+(Q65*$Q$9))) -> 0
B66: =IF(F66<>"",1+MAX($B$21:B65),"") -> 27 | C66: S201 | D66: 8"THK. CONCRETE STEM WALL W/ #4 BARS @ 10" O.C & #4 DOWEL BAR @ 18" O.C | E66: CY | F66: =194*2*0.67/27 -> 9.6281481 | G66: 366 | H66: =G66*$T$2 -> 348.432 | I66: =F66*H66 -> 3354.7549 | J66: 5.017 | K66: =F66*J66 -> 48.304419 | L66: C14D | M66: 54.81 | N66: =M66*$U$2 -> 40.06611 | O66: =J66*N66 -> 201.01167 | P66: =F66*O66 -> 1935.3702 | Q66: =I66+P66 -> 5290.1251 | R66: =Q66+(I66*$Q$7)+(P66*$Q$8)+(Q66*$Q$9)+(Q66*$Q$11)+($Q$10*(Q66+(I66*$Q$7)+(P66*$Q$8)+(Q66*$Q$9))) -> 7446.353
B67: =IF(F67<>"",1+MAX($B$21:B66),"") -> 28 | D67: 10"THK. CONCRETE STEM WALL W/ #4 BARS @ 10" O.C | E67: CY | F67: =8.5*2*0.83/27 -> 0.52259259 | G67: 366 | H67: =G67*$T$2 -> 348.432 | I67: =F67*H67 -> 182.08798 | J67: 5.017 | K67: =F67*J67 -> 2.621847 | L67: C14D | M67: 54.81 | N67: =M67*$U$2 -> 40.06611 | O67: =J67*N67 -> 201.01167 | P67: =F67*O67 -> 105.04721 | Q67: =I67+P67 -> 287.13519 | R67: =Q67+(I67*$Q$7)+(P67*$Q$8)+(Q67*$Q$9)+(Q67*$Q$11)+($Q$10*(Q67+(I67*$Q$7)+(P67*$Q$8)+(Q67*$Q$9))) -> 404.17003
B68: =IF(F68<>"",1+MAX($B$21:B67),"") | H68: =G68*$T$2 -> 0 | I68: =F68*H68 -> 0 | K68: =F68*J68 -> 0 | N68: =M68*$U$2 -> 0 | O68: =J68*N68 -> 0 | P68: =F68*O68 -> 0 | Q68: =I68+P68 -> 0 | R68: =Q68+(I68*$Q$7)+(P68*$Q$8)+(Q68*$Q$9)+(Q68*$Q$11)+($Q$10*(Q68+(I68*$Q$7)+(P68*$Q$8)+(Q68*$Q$9))) -> 0
B69: =IF(F69<>"",1+MAX($B$21:B68),"") | D69: CONCRETE PAD | H69: =G69*$T$2 -> 0 | I69: =F69*H69 -> 0 | K69: =F69*J69 -> 0 | N69: =M69*$U$2 -> 0 | O69: =J69*N69 -> 0 | P69: =F69*O69 -> 0 | Q69: =I69+P69 -> 0 | R69: =Q69+(I69*$Q$7)+(P69*$Q$8)+(Q69*$Q$9)+(Q69*$Q$11)+($Q$10*(Q69+(I69*$Q$7)+(P69*$Q$8)+(Q69*$Q$9))) -> 0
B70: =IF(F70<>"",1+MAX($B$21:B69),"") -> 29 | C70: P302 | D70: 18"x18"x6"THK. CONCRETE PAD FOR CLEAN OUT | E70: CY | F70: =1.5*1.5*0.5*1/27 -> 0.041666667 | G70: 304.22 | H70: =G70*$T$2 -> 289.61744 | I70: =F70*H70 -> 12.067393 | J70: 6.415 | K70: =F70*J70 -> 0.26729167 | L70: C14H | M70: 52.21 | N70: =M70*$U$2 -> 38.16551 | O70: =J70*N70 -> 244.83175 | P70: =F70*O70 -> 10.201323 | Q70: =I70+P70 -> 22.268716 | R70: =Q70+(I70*$Q$7)+(P70*$Q$8)+(Q70*$Q$9)+(Q70*$Q$11)+($Q$10*(Q70+(I70*$Q$7)+(P70*$Q$8)+(Q70*$Q$9))) -> 31.408196
B71: =IF(F71<>"",1+MAX($B$21:B70),"") | H71: =G71*$T$2 -> 0 | I71: =F71*H71 -> 0 | K71: =F71*J71 -> 0 | N71: =M71*$U$2 -> 0 | O71: =J71*N71 -> 0 | P71: =F71*O71 -> 0 | Q71: =I71+P71 -> 0 | R71: =Q71+(I71*$Q$7)+(P71*$Q$8)+(Q71*$Q$9)+(Q71*$Q$11)+($Q$10*(Q71+(I71*$Q$7)+(P71*$Q$8)+(Q71*$Q$9))) -> 0
B72: =IF(F72<>"",1+MAX($B$21:B71),"") | D72: FORMWORK | H72: =G72*$T$2 -> 0 | I72: =F72*H72 -> 0 | K72: =F72*J72 -> 0 | N72: =M72*$U$2 -> 0 | O72: =J72*N72 -> 0 | P72: =F72*O72 -> 0 | Q72: =I72+P72 -> 0 | R72: =Q72+(I72*$Q$7)+(P72*$Q$8)+(Q72*$Q$9)+(Q72*$Q$11)+($Q$10*(Q72+(I72*$Q$7)+(P72*$Q$8)+(Q72*$Q$9))) -> 0
B73: =IF(F73<>"",1+MAX($B$21:B72),"") -> 30 | D73: FORMWORK REQUIRED | E73: SF | F73: 1420 | G73: 2 | H73: =G73*$T$2 -> 1.904 | I73: =F73*H73 -> 2703.68 | J73: 0.037 | K73: =F73*J73 -> 52.54 | L73: 2 CARP | M73: 53.15 | N73: =M73*$U$2 -> 38.85265 | O73: =J73*N73 -> 1.437548 | P73: =F73*O73 -> 2041.3182 | Q73: =I73+P73 -> 4744.9982 | R73: =Q73+(I73*$Q$7)+(P73*$Q$8)+(Q73*$Q$9)+(Q73*$Q$11)+($Q$10*(Q73+(I73*$Q$7)+(P73*$Q$8)+(Q73*$Q$9))) -> 6688.3799
B74: =IF(F74<>"",1+MAX($B$21:B73),"") | H74: =G74*$T$2 -> 0 | I74: =F74*H74 -> 0 | K74: =F74*J74 -> 0 | N74: =M74*$U$2 -> 0 | O74: =J74*N74 -> 0 | P74: =F74*O74 -> 0 | Q74: =I74+P74 -> 0 | R74: =Q74+(I74*$Q$7)+(P74*$Q$8)+(Q74*$Q$9)+(Q74*$Q$11)+($Q$10*(Q74+(I74*$Q$7)+(P74*$Q$8)+(Q74*$Q$9))) -> 0
B75: =IF(F75<>"",1+MAX($B$21:B74),"") | C75: DIV. 04 | D75: MASONRY | H75: SUBTOTAL MATERIAL | I75: =SUM(I76:I89) -> 4411.962 | K75: =ROUND(SUM(K76:K89),0) & " " & "HRS" -> 224 HRS | O75: SUBTOTAL LABOR | P75: =SUM(P76:P89) -> 7798.6141 | Q75: =SUM(Q76:Q89) -> 12210.576 | R75: =(Q75)+(I75*$Q$7)+(P75*$Q$8)+(Q75*$Q$9)+($Q$10*((Q75)+(I75*$Q$7)+(P75*$Q$8)+(Q75*$Q$9)))+(Q75*$Q$11) -> 17289.486
B76: =IF(F76<>"",1+MAX($B$21:B75),"") | H76: =G76*$T$2 -> 0 | I76: =F76*H76 -> 0 | K76: =F76*J76 -> 0 | N76: =M76*$U$2 -> 0 | O76: =J76*N76 -> 0 | P76: =F76*O76 -> 0 | Q76: =I76+P76 -> 0 | R76: =Q76+(I76*$Q$7)+(P76*$Q$8)+(Q76*$Q$9)+(Q76*$Q$11)+($Q$10*(Q76+(I76*$Q$7)+(P76*$Q$8)+(Q76*$Q$9))) -> 0
B77: =IF(F77<>"",1+MAX($B$21:B76),"") | D77: CMU | H77: =G77*$T$2 -> 0 | I77: =F77*H77 -> 0 | K77: =F77*J77 -> 0 | N77: =M77*$U$2 -> 0 | O77: =J77*N77 -> 0 | P77: =F77*O77 -> 0 | Q77: =I77+P77 -> 0 | R77: =Q77+(I77*$Q$7)+(P77*$Q$8)+(Q77*$Q$9)+(Q77*$Q$11)+($Q$10*(Q77+(I77*$Q$7)+(P77*$Q$8)+(Q77*$Q$9))) -> 0
B78: =IF(F78<>"",1+MAX($B$21:B77),"") -> 31 | C78: A110 | D78: 4"THK. FULLY GROUTED CMU STEM WALL W/ GROUT CAVITY SOLID | E78: SF | F78: =157.5*1.33 -> 209.475 | G78: 3.03 | H78: =G78*$T$2 -> 2.88456 | I78: =F78*H78 -> 604.24321 | J78: 0.165 | K78: =F78*J78 -> 34.563375 | L78: D-9 | M78: 46.9 | N78: =M78*$U$2 -> 34.2839 | O78: =J78*N78 -> 5.6568435 | P78: =F78*O78 -> 1184.9673 | Q78: =I78+P78 -> 1789.2105 | R78: =Q78+(I78*$Q$7)+(P78*$Q$8)+(Q78*$Q$9)+(Q78*$Q$11)+($Q$10*(Q78+(I78*$Q$7)+(P78*$Q$8)+(Q78*$Q$9))) -> 2534.7135
B79: =IF(F79<>"",1+MAX($B$21:B78),"") | H79: =G79*$T$2 -> 0 | I79: =F79*H79 -> 0 | K79: =F79*J79 -> 0 | N79: =M79*$U$2 -> 0 | O79: =J79*N79 -> 0 | P79: =F79*O79 -> 0 | Q79: =I79+P79 -> 0 | R79: =Q79+(I79*$Q$7)+(P79*$Q$8)+(Q79*$Q$9)+(Q79*$Q$11)+($Q$10*(Q79+(I79*$Q$7)+(P79*$Q$8)+(Q79*$Q$9))) -> 0
B80: =IF(F80<>"",1+MAX($B$21:B79),"") | D80: EXTERIOR FINISH | H80: =G80*$T$2 -> 0 | I80: =F80*H80 -> 0 | K80: =F80*J80 -> 0 | N80: =M80*$U$2 -> 0 | O80: =J80*N80 -> 0 | P80: =F80*O80 -> 0 | Q80: =I80+P80 -> 0 | R80: =Q80+(I80*$Q$7)+(P80*$Q$8)+(Q80*$Q$9)+(Q80*$Q$11)+($Q$10*(Q80+(I80*$Q$7)+(P80*$Q$8)+(Q80*$Q$9))) -> 0
B81: =IF(F81<>"",1+MAX($B$21:B80),"") -> 32 | C81: A200, A201 | D81: 3-5/8"THK. STANDARD MODULAR BRICK VENEER W/ ADJUSTABLE BRICK TIES @ 32"O.C HORIZOANTAL & 16" VERTICAL MFR: ACME BRICL COLOR: SLATE GRAY - MORTAR MANUFACTURER: COOSA, MORTAR COLOR: OLD LIME PUTTY | E81: SF | F81: 400 | G81: 6.63 | H81: =G81*$T$2 -> 6.31176 | I81: =F81*H81 -> 2524.704 | J81: 0.335 | K81: =F81*J81 -> 134 | L81: D-8 | M81: 47.93 | N81: =M81*$U$2 -> 35.03683 | O81: =J81*N81 -> 11.737338 | P81: =F81*O81 -> 4694.9352 | Q81: =I81+P81 -> 7219.6392 | R81: =Q81+(I81*$Q$7)+(P81*$Q$8)+(Q81*$Q$9)+(Q81*$Q$11)+($Q$10*(Q81+(I81*$Q$7)+(P81*$Q$8)+(Q81*$Q$9))) -> 10225.169
B82: =IF(F82<>"",1+MAX($B$21:B81),"") | H82: =G82*$T$2 -> 0 | I82: =F82*H82 -> 0 | K82: =F82*J82 -> 0 | N82: =M82*$U$2 -> 0 | O82: =J82*N82 -> 0 | P82: =F82*O82 -> 0 | Q82: =I82+P82 -> 0 | R82: =Q82+(I82*$Q$7)+(P82*$Q$8)+(Q82*$Q$9)+(Q82*$Q$11)+($Q$10*(Q82+(I82*$Q$7)+(P82*$Q$8)+(Q82*$Q$9))) -> 0
B83: =IF(F83<>"",1+MAX($B$21:B82),"") | D83: ROWLOCK | H83: =G83*$T$2 -> 0 | I83: =F83*H83 -> 0 | K83: =F83*J83 -> 0 | N83: =M83*$U$2 -> 0 | O83: =J83*N83 -> 0 | P83: =F83*O83 -> 0 | Q83: =I83+P83 -> 0 | R83: =Q83+(I83*$Q$7)+(P83*$Q$8)+(Q83*$Q$9)+(Q83*$Q$11)+($Q$10*(Q83+(I83*$Q$7)+(P83*$Q$8)+(Q83*$Q$9))) -> 0
B84: =IF(F84<>"",1+MAX($B$21:B83),"") -> 33 | D84: 3-1/4"THK. x 3-5/8"H HALF ROWLOCK BRICK | E84: LF | F84: 149.33 | G84: 1.8 | H84: =G84*$T$2 -> 1.7136 | I84: =F84*H84 -> 255.89189 | J84: 0.091 | K84: =F84*J84 -> 13.58903 | L84: D-8 | M84: 47.93 | N84: =M84*$U$2 -> 35.03683 | O84: =J84*N84 -> 3.1883515 | P84: =F84*O84 -> 476.11653 | Q84: =I84+P84 -> 732.00842 | R84: =Q84+(I84*$Q$7)+(P84*$Q$8)+(Q84*$Q$9)+(Q84*$Q$11)+($Q$10*(Q84+(I84*$Q$7)+(P84*$Q$8)+(Q84*$Q$9))) -> 1036.7457
B85: =IF(F85<>"",1+MAX($B$21:B84),"") -> 34 | D85: 7-5/8"THK. x 3-5/8"H ROWLOCK SILL | E85: LF | F85: 149.86 | G85: 4.21 | H85: =G85*$T$2 -> 4.00792 | I85: =F85*H85 -> 600.62689 | J85: 0.213 | K85: =F85*J85 -> 31.92018 | L85: D-8 | M85: 47.93 | N85: =M85*$U$2 -> 35.03683 | O85: =J85*N85 -> 7.4628448 | P85: =F85*O85 -> 1118.3819 | Q85: =I85+P85 -> 1719.0088 | R85: =Q85+(I85*$Q$7)+(P85*$Q$8)+(Q85*$Q$9)+(Q85*$Q$11)+($Q$10*(Q85+(I85*$Q$7)+(P85*$Q$8)+(Q85*$Q$9))) -> 2434.6464
B86: =IF(F86<>"",1+MAX($B$21:B85),"") | H86: =G86*$T$2 -> 0 | I86: =F86*H86 -> 0 | K86: =F86*J86 -> 0 | N86: =M86*$U$2 -> 0 | O86: =J86*N86 -> 0 | P86: =F86*O86 -> 0 | Q86: =I86+P86 -> 0 | R86: =Q86+(I86*$Q$7)+(P86*$Q$8)+(Q86*$Q$9)+(Q86*$Q$11)+($Q$10*(Q86+(I86*$Q$7)+(P86*$Q$8)+(Q86*$Q$9))) -> 0
B87: =IF(F87<>"",1+MAX($B$21:B86),"") | D87: VAPOR BARRIER | H87: =G87*$T$2 -> 0 | I87: =F87*H87 -> 0 | K87: =F87*J87 -> 0 | N87: =M87*$U$2 -> 0 | O87: =J87*N87 -> 0 | P87: =F87*O87 -> 0 | Q87: =I87+P87 -> 0 | R87: =Q87+(I87*$Q$7)+(P87*$Q$8)+(Q87*$Q$9)+(Q87*$Q$11)+($Q$10*(Q87+(I87*$Q$7)+(P87*$Q$8)+(Q87*$Q$9))) -> 0
B88: =IF(F88<>"",1+MAX($B$21:B87),"") -> 35 | D88: LUID APPLIED VAPOR BARRIER | E88: SF | F88: 400 | G88: 1.12 | H88: =G88*$T$2 -> 1.06624 | I88: =F88*H88 -> 426.496 | J88: 0.024 | K88: =F88*J88 -> 9.6 | L88: 2 ROFC | M88: 46.2 | N88: =M88*$U$2 -> 33.7722 | O88: =J88*N88 -> 0.8105328 | P88: =F88*O88 -> 324.21312 | Q88: =I88+P88 -> 750.70912 | R88: =Q88+(I88*$Q$7)+(P88*$Q$8)+(Q88*$Q$9)+(Q88*$Q$11)+($Q$10*(Q88+(I88*$Q$7)+(P88*$Q$8)+(Q88*$Q$9))) -> 1058.2111
B89: =IF(F89<>"",1+MAX($B$21:B88),"") | H89: =G89*$T$2 -> 0 | I89: =F89*H89 -> 0 | K89: =F89*J89 -> 0 | N89: =M89*$U$2 -> 0 | O89: =J89*N89 -> 0 | P89: =F89*O89 -> 0 | Q89: =I89+P89 -> 0 | R89: =Q89+(I89*$Q$7)+(P89*$Q$8)+(Q89*$Q$9)+(Q89*$Q$11)+($Q$10*(Q89+(I89*$Q$7)+(P89*$Q$8)+(Q89*$Q$9))) -> 0
B90: =IF(F90<>"",1+MAX($B$21:B89),"") | C90: DIV. 05 | D90: METALS | H90: SUBTOTAL MATERIAL | I90: =SUM(I91:I154) -> 64578.275 | K90: =ROUND(SUM(K91:K154),0) & " " & "HRS" -> 777 HRS | O90: SUBTOTAL LABOR | P90: =SUM(P91:P154) -> 40678.918 | Q90: =SUM(Q91:Q154) -> 105257.19 | R90: =(Q90)+(I90*$Q$7)+(P90*$Q$8)+(Q90*$Q$9)+($Q$10*((Q90)+(I90*$Q$7)+(P90*$Q$8)+(Q90*$Q$9)))+(Q90*$Q$11) -> 148225.92
B91: =IF(F91<>"",1+MAX($B$21:B90),"") | H91: =G91*$T$2 -> 0 | I91: =F91*H91 -> 0 | K91: =F91*J91 -> 0 | N91: =M91*$U$2 -> 0 | O91: =J91*N91 -> 0 | P91: =F91*O91 -> 0 | Q91: =I91+P91 -> 0 | R91: =Q91+(I91*$Q$7)+(P91*$Q$8)+(Q91*$Q$9)+(Q91*$Q$11)+($Q$10*(Q91+(I91*$Q$7)+(P91*$Q$8)+(Q91*$Q$9))) -> 0
B92: =IF(F92<>"",1+MAX($B$21:B91),"") | D92: COLUMN | H92: =G92*$T$2 -> 0 | I92: =F92*H92 -> 0 | K92: =F92*J92 -> 0 | N92: =M92*$U$2 -> 0 | O92: =J92*N92 -> 0 | P92: =F92*O92 -> 0 | Q92: =I92+P92 -> 0 | R92: =Q92+(I92*$Q$7)+(P92*$Q$8)+(Q92*$Q$9)+(Q92*$Q$11)+($Q$10*(Q92+(I92*$Q$7)+(P92*$Q$8)+(Q92*$Q$9))) -> 0
B93: =IF(F93<>"",1+MAX($B$21:B92),"") -> 36 | C93: S203 - S301 | D93: HSS1-1/2"x1-1/2"x3/16" TUBE COLUMN | E93: LF | F93: =6*1.58 -> 9.48 | G93: 5.47 | H93: =G93*$T$2 -> 5.20744 | I93: =F93*H93 -> 49.366531 | J93: 0.04 | K93: =F93*J93 -> 0.3792 | L93: E-2 | M93: 87.43 | N93: =M93*$U$2 -> 63.91133 | O93: =J93*N93 -> 2.5564532 | P93: =F93*O93 -> 24.235176 | Q93: =I93+P93 -> 73.601708 | R93: =Q93+(I93*$Q$7)+(P93*$Q$8)+(Q93*$Q$9)+(Q93*$Q$11)+($Q$10*(Q93+(I93*$Q$7)+(P93*$Q$8)+(Q93*$Q$9))) -> 103.51902
B94: =IF(F94<>"",1+MAX($B$21:B93),"") -> 37 | D94: HSS4x4x1/4 COLUMN | E94: LF | F94: =6*1.33+5.62 -> 13.6 | G94: 21.98 | H94: =G94*$T$2 -> 20.92496 | I94: =F94*H94 -> 284.57946 | J94: 0.159 | K94: =F94*J94 -> 2.1624 | L94: E-2 | M94: 87.43 | N94: =M94*$U$2 -> 63.91133 | O94: =J94*N94 -> 10.161901 | P94: =F94*O94 -> 138.20186 | Q94: =I94+P94 -> 422.78132 | R94: =Q94+(I94*$Q$7)+(P94*$Q$8)+(Q94*$Q$9)+(Q94*$Q$11)+($Q$10*(Q94+(I94*$Q$7)+(P94*$Q$8)+(Q94*$Q$9))) -> 594.60081
B95: =IF(F95<>"",1+MAX($B$21:B94),"") -> 38 | D95: HSS5x5x3/8 COLUMN | E95: LF | F95: 39.14 | G95: 40.27 | H95: =G95*$T$2 -> 38.33704 | I95: =F95*H95 -> 1500.5117 | J95: 0.291 | K95: =F95*J95 -> 11.38974 | L95: E-2 | M95: 87.43 | N95: =M95*$U$2 -> 63.91133 | O95: =J95*N95 -> 18.598197 | P95: =F95*O95 -> 727.93343 | Q95: =I95+P95 -> 2228.4452 | R95: =Q95+(I95*$Q$7)+(P95*$Q$8)+(Q95*$Q$9)+(Q95*$Q$11)+($Q$10*(Q95+(I95*$Q$7)+(P95*$Q$8)+(Q95*$Q$9))) -> 3134.0756
B96: =IF(F96<>"",1+MAX($B$21:B95),"") -> 39 | D96: HSS6x6x1/2 COLUMN | E96: LF | F96: 19.72 | G96: 63.43 | H96: =G96*$T$2 -> 60.38536 | I96: =F96*H96 -> 1190.7993 | J96: 0.458 | K96: =F96*J96 -> 9.03176 | L96: E-2 | M96: 87.43 | N96: =M96*$U$2 -> 63.91133 | O96: =J96*N96 -> 29.271389 | P96: =F96*O96 -> 577.23179 | Q96: =I96+P96 -> 1768.0311 | R96: =Q96+(I96*$Q$7)+(P96*$Q$8)+(Q96*$Q$9)+(Q96*$Q$11)+($Q$10*(Q96+(I96*$Q$7)+(P96*$Q$8)+(Q96*$Q$9))) -> 2486.5419
B97: =IF(F97<>"",1+MAX($B$21:B96),"") -> 40 | D97: HSS6x6x3/8 COLUMN | E97: LF | F97: 236.34 | G97: 49.46 | H97: =G97*$T$2 -> 47.08592 | I97: =F97*H97 -> 11128.286 | J97: 0.357 | K97: =F97*J97 -> 84.37338 | L97: E-2 | M97: 87.43 | N97: =M97*$U$2 -> 63.91133 | O97: =J97*N97 -> 22.816345 | P97: =F97*O97 -> 5392.4149 | Q97: =I97+P97 -> 16520.701 | R97: =Q97+(I97*$Q$7)+(P97*$Q$8)+(Q97*$Q$9)+(Q97*$Q$11)+($Q$10*(Q97+(I97*$Q$7)+(P97*$Q$8)+(Q97*$Q$9))) -> 23234.515
B98: =IF(F98<>"",1+MAX($B$21:B97),"") -> 41 | D98: HSS7x7x1/2 COLUMN | E98: LF | F98: 97.3 | G98: 75.69 | H98: =G98*$T$2 -> 72.05688 | I98: =F98*H98 -> 7011.1344 | J98: 0.547 | K98: =F98*J98 -> 53.2231 | L98: E-2 | M98: 87.43 | N98: =M98*$U$2 -> 63.91133 | O98: =J98*N98 -> 34.959498 | P98: =F98*O98 -> 3401.5591 | Q98: =I98+P98 -> 10412.694 | R98: =Q98+(I98*$Q$7)+(P98*$Q$8)+(Q98*$Q$9)+(Q98*$Q$11)+($Q$10*(Q98+(I98*$Q$7)+(P98*$Q$8)+(Q98*$Q$9))) -> 14644.373
B99: =IF(F99<>"",1+MAX($B$21:B98),"") | H99: =G99*$T$2 -> 0 | I99: =F99*H99 -> 0 | K99: =F99*J99 -> 0 | N99: =M99*$U$2 -> 0 | O99: =J99*N99 -> 0 | P99: =F99*O99 -> 0 | Q99: =I99+P99 -> 0 | R99: =Q99+(I99*$Q$7)+(P99*$Q$8)+(Q99*$Q$9)+(Q99*$Q$11)+($Q$10*(Q99+(I99*$Q$7)+(P99*$Q$8)+(Q99*$Q$9))) -> 0
B100: =IF(F100<>"",1+MAX($B$21:B99),"") | D100: BEAM | H100: =G100*$T$2 -> 0 | I100: =F100*H100 -> 0 | K100: =F100*J100 -> 0 | N100: =M100*$U$2 -> 0 | O100: =J100*N100 -> 0 | P100: =F100*O100 -> 0 | Q100: =I100+P100 -> 0 | R100: =Q100+(I100*$Q$7)+(P100*$Q$8)+(Q100*$Q$9)+(Q100*$Q$11)+($Q$10*(Q100+(I100*$Q$7)+(P100*$Q$8)+(Q100*$Q$9))) -> 0
...
